{"status": "RESOLVED", "cf_tracking_firefox60": "---", "attachments": [], "classification": "Client Software", "creator": "mmucci@mozilla.com", "cc": ["gijskruitbosch+bugs@gmail.com", "mmaslaney@mozilla.com", "mmucci@mozilla.com", "mstange@themasta.com", "Nomis101@web.de", "philipp@mozilla.com"], "depends_on": [1053176], "creation_time": "2014-08-19T13:25:26Z", "cf_user_story": "", "cf_tracking_firefox_relnote": "---", "platform": "All", "cf_status_firefox58": "---", "cf_status_firefox59": "---", "keywords": [], "summary": "[10.10] [UX] Investigate updating hover state for buttons in the tabstrip", "cf_last_resolved": "2014-10-23T17:08:49Z", "assigned_to_detail": {"email": "mmaslaney@mozilla.com", "id": 455531, "name": "mmaslaney@mozilla.com", "real_name": "Michael Maslaney [:mmaslaney] (mmaslaney@mozilla.com)"}, "severity": "normal", "is_confirmed": true, "is_creator_accessible": true, "cf_has_regression_range": "---", "assigned_to": "mmaslaney@mozilla.com", "comment_count": 4, "comments": [{"text": "+++ This bug was initially created as a clone of Bug #1053073 +++", "author": "mmucci@mozilla.com", "id": 9200475, "time": "2014-08-19T13:25:26Z"}, {"text": "Below are mocks of the OSX 10.10 Yoesimite theme utilizing our previous 10.9 assets. As you can see, the transparent assets for our previous OSX versions integrate quite nicely with the new theme. Therefore, my recommendation is to continue using tabstrip assets from the previous theme.\n\nExamples\n\nNew tab: http://people.mozilla.org/~mmaslaney/firefox/OSX-Yosemite-newtab\n\nHighlight: http://people.mozilla.org/~mmaslaney/firefox/OSX-Yosemite-highlight", "author": "mmaslaney@mozilla.com", "id": 9485048, "time": "2014-10-22T15:34:49Z"}, {"text": "(In reply to mmaslaney from comment #1)\n> Below are mocks of the OSX 10.10 Yoesimite theme utilizing our previous 10.9\n> assets. As you can see, the transparent assets for our previous OSX versions\n> integrate quite nicely with the new theme. Therefore, my recommendation is\n> to continue using tabstrip assets from the previous theme.\n> \n> Examples\n> \n> New tab: http://people.mozilla.org/~mmaslaney/firefox/OSX-Yosemite-newtab\n> \n> Highlight:\n> http://people.mozilla.org/~mmaslaney/firefox/OSX-Yosemite-highlight\n\nI was more worried about buttons, when moved to the tab bar. They look like this: http://imgur.com/QPMX662\n\nThe transparent grey might not work well on the tab bar?", "author": "gijskruitbosch+bugs@gmail.com", "id": 9485246, "time": "2014-10-22T16:04:37Z"}, {"text": "I would stick with the pre-existing assets.\n\n\nSee mockup: http://people.mozilla.org/~mmaslaney/firefox/OSX-Yosemite-highlight-overflow.png", "author": "mmaslaney@mozilla.com", "id": 9487130, "time": "2014-10-22T20:48:33Z"}], "id": 1055523, "priority": "--", "mentors_detail": [], "cf_crash_signature": "", "version": "Trunk", "cf_qa_whiteboard": "", "cf_tracking_firefox_esr52": "---", "cf_tracking_firefox59": "---", "last_change_time": "2014-10-23T17:08:49Z", "cf_platform_rel": "---", "product": "Firefox", "cf_status_firefox_esr52": "---", "blocks": [1053073], "qa_contact": "", "see_also": [], "cf_fx_iteration": "36.1", "component": "Theme", "votes": 0, "groups": [], "cf_status_firefox60": "---", "target_milestone": "---", "is_cc_accessible": true, "url": "", "creator_detail": {"email": "mmucci@mozilla.com", "id": 458208, "name": "mmucci@mozilla.com", "real_name": "Marco Mucci [:MarcoM]"}, "whiteboard": "[ux]", "mentors": [], "cc_detail": [{"email": "gijskruitbosch+bugs@gmail.com", "id": 159069, "name": "gijskruitbosch+bugs@gmail.com", "real_name": ":Gijs (under the weather; responses will be slow)"}, {"email": "mmaslaney@mozilla.com", "id": 455531, "name": "mmaslaney@mozilla.com", "real_name": "Michael Maslaney [:mmaslaney] (mmaslaney@mozilla.com)"}, {"email": "mmucci@mozilla.com", "id": 458208, "name": "mmucci@mozilla.com", "real_name": "Marco Mucci [:MarcoM]"}, {"email": "mstange@themasta.com", "id": 293943, "name": "mstange@themasta.com", "real_name": "Markus Stange [:mstange]"}, {"email": "Nomis101@web.de", "id": 299163, "name": "Nomis101@web.de", "real_name": "Nomis101"}, {"email": "philipp@mozilla.com", "id": 485651, "name": "philipp@mozilla.com", "real_name": "(Currently slow to respond) Philipp Sackl [:phlsa] (Firefox UX) please use needinfo"}], "cf_has_str": "---", "alias": null, "dupe_of": null, "flags": [{"status": "+", "name": "firefox-backlog", "modification_date": "2014-08-19T13:25:26Z", "type_id": 846, "creation_date": "2014-08-19T13:25:26Z", "id": 954653, "setter": "mmucci@mozilla.com"}, {"status": "-", "name": "qe-verify", "modification_date": "2014-08-19T13:25:26Z", "type_id": 864, "creation_date": "2014-08-19T13:25:26Z", "id": 954654, "setter": "mmucci@mozilla.com"}], "cf_tracking_firefox58": "---", "cf_rank": null, "is_open": false, "resolution": "FIXED", "op_sys": "All", "cf_fx_points": "5", "history": [{"changes": [{"removed": "", "field_name": "flagtypes.name", "added": "firefox-backlog+, qe-verify-"}], "who": "mmucci@mozilla.com", "when": "2014-08-19T13:25:26Z"}, {"changes": [{"removed": "", "field_name": "cc", "added": "mmucci@mozilla.com"}], "who": "mmucci@mozilla.com", "when": "2014-08-19T13:26:40Z"}, {"changes": [{"removed": "", "field_name": "cc", "added": "gijskruitbosch+bugs@gmail.com"}, {"removed": "", "field_name": "depends_on", "added": "1053176"}], "who": "gijskruitbosch+bugs@gmail.com", "when": "2014-08-19T13:33:05Z"}, {"changes": [{"removed": "", "field_name": "cc", "added": "mstange@themasta.com"}], "who": "mstange@themasta.com", "when": "2014-08-19T13:35:10Z"}, {"changes": [{"removed": "", "field_name": "cc", "added": "Nomis101@web.de"}], "who": "Nomis101@web.de", "when": "2014-08-19T14:35:18Z"}, {"changes": [{"removed": "NEW", "field_name": "status", "added": "ASSIGNED"}, {"removed": "---", "field_name": "cf_fx_points", "added": "5"}, {"removed": "---", "field_name": "cf_fx_iteration", "added": "36.1"}, {"removed": "nobody@mozilla.org", "field_name": "assigned_to", "added": "mmaslaney@mozilla.com"}], "who": "mmucci@mozilla.com", "when": "2014-10-14T16:09:17Z"}, {"changes": [{"removed": "", "field_name": "cc", "added": "mmaslaney@mozilla.com"}, {"removed": "", "field_name": "flagtypes.name", "added": "needinfo?(mmaslaney@mozilla.com)"}], "who": "gijskruitbosch+bugs@gmail.com", "when": "2014-10-22T16:04:37Z"}, {"changes": [{"removed": "needinfo?(mmaslaney@mozilla.com)", "field_name": "flagtypes.name", "added": ""}], "who": "mmaslaney@mozilla.com", "when": "2014-10-22T20:48:33Z"}, {"changes": [{"removed": "ASSIGNED", "field_name": "status", "added": "RESOLVED"}, {"removed": "", "field_name": "resolution", "added": "FIXED"}, {"removed": "", "field_name": "cf_last_resolved", "added": "2014-10-23 10:08:49"}], "who": "mmaslaney@mozilla.com", "when": "2014-10-23T17:08:49Z"}]}