{"cf_tracking_thunderbird_esr52": "---", "status": "RESOLVED", "cf_tracking_firefox60": "---", "cf_tracking_firefox61": "---", "cf_tracking_firefox62": "---", "creator": "dholbert@mozilla.com", "mentors_detail": [], "depends_on": [], "cf_status_firefox32": "---", "cf_status_firefox33": "---", "cf_status_firefox_esr60": "---", "cf_status_firefox35": "---", "cf_status_firefox36": "---", "cf_user_story": "", "cf_backlog": "---", "creation_time": "2014-11-13T16:15:34Z", "cf_tracking_firefox_relnote": "---", "platform": "All", "keywords": [], "cf_fx_iteration": "---", "cc_detail": [{"email": "dkeeler@mozilla.com", "id": 349244, "name": "dkeeler@mozilla.com", "real_name": "[:keeler] (use needinfo)"}, {"email": "edwin.bugs@flores.geek.nz", "id": 430065, "name": "edwin.bugs@flores.geek.nz", "real_name": "Edwin Flores [inactive from 2016-12-01] [:eflores] [:edwin]"}, {"email": "jyavenard@mozilla.com", "id": 512198, "name": "jyavenard@mozilla.com", "real_name": "Jean-Yves Avenard [:jya]"}], "cf_last_resolved": "2014-11-14T22:54:33Z", "attachments": [{"creator": "dholbert@mozilla.com", "is_obsolete": 0, "is_patch": 1, "flags": [{"status": "+", "name": "review", "modification_date": "2014-11-14T11:10:24Z", "type_id": 4, "creation_date": "2014-11-13T16:21:07Z", "id": 1032836, "setter": "edwin.bugs@flores.geek.nz"}], "content_type": "text/plain", "id": 8522292}], "votes": 0, "classification": "Components", "is_confirmed": true, "is_creator_accessible": true, "cf_has_regression_range": "---", "comment_count": 8, "comments": [{"text": "New build warning (treated as an error in --enable-warnings-as-errors builds), with clang 3.5:\n{\ndom/media/fmp4/ffmpeg/libav54/../FFmpegAudioDecoder.h:38:42: error: private field 'mConfig' is not used [-Werror,-Wunused-private-field]\n 1:01.93   const mp4_demuxer::AudioDecoderConfig& mConfig;\n 1:01.93                                          ^\n 1:01.93 1 error generated.\n}\n\n\nLooks like the last usage of this \"mConfig\" variable was just removed yesterday, in bug 1096764:\n https://hg.mozilla.org/mozilla-central/rev/1ab82eabedf0#l1.33\n\nI guess we should just get rid of this member-var, since that change left it unused (?)", "author": "dholbert@mozilla.com", "id": 9586286, "time": "2014-11-13T16:15:34Z"}, {"text": "In particular, it looks like that changeset made it so we'll now get everything we need out of the \"config\" object during the constructor.\n\nSo it makes sense that we don't need to hold onto it in a member-var.", "author": "dholbert@mozilla.com", "id": 9586299, "time": "2014-11-13T16:17:05Z"}, {"text": "Created attachment 8522292\nfix: drop the variable", "author": "dholbert@mozilla.com", "id": 9586321, "time": "2014-11-13T16:21:07Z"}, {"text": "oh.. I've done it in bug 1098637 while at it ...", "author": "jyavenard@mozilla.com", "id": 9591415, "time": "2014-11-14T11:37:15Z"}, {"text": "Ah, gotcha.  We could land them separately or just land your existing patch over there, then, I guess.\n\nI lean slightly towards landing this separately[1], because if we end up having to back out bug 1098637 (e.g. because it breaks a test or causes something unexpected), it'd be nice to still have this build error stay fixed.\n\nWould that be OK?  (It means your patch will bitrot slightly, but it looks like the bitrot should be easy because the chunks that won't apply are literally just the chunks that are the same as this patch.)", "author": "dholbert@mozilla.com", "id": 9592343, "time": "2014-11-14T16:03:53Z"}, {"text": "Actually, I just went ahead and pushed this change, since it's better to have it fixed sooner (to fix breakage in clang3.5 warnings-as-errors builds) instead of waiting on a back-and-forth here, and per comment 4, I think it's strictly better to have this de-coupled from an actual functional change.\n\nPush: https://hg.mozilla.org/integration/mozilla-inbound/rev/76fc2a130baa\n\nSorry for causing (minor) bitrot in bug 1098637. :)", "author": "dholbert@mozilla.com", "id": 9592557, "time": "2014-11-14T16:48:02Z"}, {"text": "*** Bug 1099225 has been marked as a duplicate of this bug. ***", "author": "giles@thaumas.net", "id": 9592737, "time": "2014-11-14T17:31:56Z"}, {"text": "https://hg.mozilla.org/mozilla-central/rev/76fc2a130baa", "author": "ryanvm@gmail.com", "id": 9594282, "time": "2014-11-14T22:54:33Z"}], "id": 1098400, "priority": "--", "cc": ["dkeeler@mozilla.com", "edwin.bugs@flores.geek.nz", "jyavenard@mozilla.com"], "cf_crash_signature": "", "version": "Trunk", "is_cc_accessible": true, "cf_tracking_firefox_esr52": "---", "see_also": [], "cf_tracking_thunderbird_esr60": "---", "cf_platform_rel": "---", "product": "Core", "cf_status_firefox_esr52": "---", "blocks": [187528], "qa_contact": "", "cf_has_str": "---", "cf_tracking_firefox35": "---", "cf_tracking_firefox34": "---", "component": "Audio/Video", "assigned_to_detail": {"email": "dholbert@mozilla.com", "id": 278074, "name": "dholbert@mozilla.com", "real_name": "Daniel Holbert [:dholbert]"}, "cf_tracking_firefox_esr60": "---", "cf_status_firefox34": "---", "cf_status_firefox62": "---", "cf_status_firefox61": "---", "cf_status_firefox60": "---", "target_milestone": "mozilla36", "cf_rank": null, "cf_qa_whiteboard": "", "severity": "normal", "groups": [], "cf_status_thunderbird_esr52": "---", "url": "", "cf_status_thunderbird_esr60": "---", "creator_detail": {"email": "dholbert@mozilla.com", "id": 278074, "name": "dholbert@mozilla.com", "real_name": "Daniel Holbert [:dholbert]"}, "whiteboard": "", "mentors": [], "summary": "FFmpegAudioDecoder.h:38:42: error: private field 'mConfig' is not used [-Werror,-Wunused-private-field]", "alias": null, "dupe_of": null, "flags": [{"status": "-", "name": "in-testsuite", "modification_date": "2014-11-14T16:48:02Z", "type_id": 37, "creation_date": "2014-11-14T16:48:02Z", "id": 1034002, "setter": "dholbert@mozilla.com"}], "last_change_time": "2014-11-14T22:54:33Z", "assigned_to": "dholbert@mozilla.com", "is_open": false, "history": [{"changes": [{"removed": "", "field_name": "cc", "added": "edwin@mozilla.com"}, {"removed": "nobody@mozilla.org", "field_name": "assigned_to", "added": "dholbert@mozilla.com"}, {"field_name": "flagtypes.name", "removed": "", "attachment_id": 8522292, "added": "review?(edwin@mozilla.com)"}, {"removed": "NEW", "field_name": "status", "added": "ASSIGNED"}], "who": "dholbert@mozilla.com", "when": "2014-11-13T16:21:07Z"}, {"changes": [{"field_name": "flagtypes.name", "removed": "review?(edwin@mozilla.com)", "attachment_id": 8522292, "added": "review+"}], "who": "edwin.bugs@flores.geek.nz", "when": "2014-11-14T11:10:24Z"}, {"changes": [{"removed": "", "field_name": "flagtypes.name", "added": "needinfo?(jyavenard@mozilla.com)"}], "who": "dholbert@mozilla.com", "when": "2014-11-14T16:11:57Z"}, {"changes": [{"removed": "", "field_name": "blocks", "added": "187528"}, {"removed": "needinfo?(jyavenard@mozilla.com)", "field_name": "flagtypes.name", "added": "in-testsuite-"}], "who": "dholbert@mozilla.com", "when": "2014-11-14T16:48:02Z"}, {"changes": [{"removed": "", "field_name": "cc", "added": "dkeeler@mozilla.com"}], "who": "giles@thaumas.net", "when": "2014-11-14T17:31:56Z"}, {"changes": [{"removed": "ASSIGNED", "field_name": "status", "added": "RESOLVED"}, {"removed": "", "field_name": "resolution", "added": "FIXED"}, {"removed": "---", "field_name": "target_milestone", "added": "mozilla36"}, {"removed": "", "field_name": "cf_last_resolved", "added": "2014-11-14 14:54:33"}], "who": "ryanvm@gmail.com", "when": "2014-11-14T22:54:33Z"}], "resolution": "FIXED", "op_sys": "All", "cf_fx_points": "---", "cf_blocking_fennec": "---"}