{"status": "RESOLVED", "cf_tracking_firefox60": "---", "attachments": [{"creator": "ntim.bugs@gmail.com", "is_obsolete": 1, "is_patch": 1, "flags": [], "content_type": "text/plain", "id": 8646975}, {"creator": "ntim.bugs@gmail.com", "is_obsolete": 1, "is_patch": 1, "flags": [], "content_type": "text/plain", "id": 8646976}, {"creator": "ntim.bugs@gmail.com", "is_obsolete": 1, "is_patch": 1, "flags": [{"status": "+", "name": "review", "modification_date": "2015-08-14T12:44:03Z", "type_id": 748, "creation_date": "2015-08-13T08:59:26Z", "id": 1231113, "setter": "mratcliffe@mozilla.com"}], "content_type": "text/plain", "id": 8647385}, {"creator": "ntim.bugs@gmail.com", "is_obsolete": 1, "is_patch": 1, "flags": [{"status": "+", "name": "review", "modification_date": "2015-09-03T23:07:47Z", "type_id": 748, "creation_date": "2015-09-03T23:07:47Z", "id": 1246050, "setter": "ntim.bugs@gmail.com"}], "content_type": "text/plain", "id": 8656871}, {"creator": "ntim.bugs@gmail.com", "is_obsolete": 1, "is_patch": 1, "flags": [], "content_type": "text/plain", "id": 8657630}, {"creator": "ntim.bugs@gmail.com", "is_obsolete": 1, "is_patch": 1, "flags": [{"status": "+", "name": "review", "modification_date": "2015-09-06T22:08:53Z", "type_id": 748, "creation_date": "2015-09-06T22:08:53Z", "id": 1246999, "setter": "ntim.bugs@gmail.com"}], "content_type": "text/plain", "id": 8657631}, {"creator": "ntim.bugs@gmail.com", "is_obsolete": 1, "is_patch": 1, "flags": [{"status": "+", "name": "review", "modification_date": "2015-09-07T07:13:20Z", "type_id": 748, "creation_date": "2015-09-06T22:09:57Z", "id": 1247000, "setter": "mratcliffe@mozilla.com"}], "content_type": "text/plain", "id": 8657632}, {"creator": "ntim.bugs@gmail.com", "is_obsolete": 1, "is_patch": 1, "flags": [{"status": "+", "name": "review", "modification_date": "2016-01-07T21:18:32Z", "type_id": 748, "creation_date": "2016-01-07T21:18:32Z", "id": 1319075, "setter": "ntim.bugs@gmail.com"}], "content_type": "text/plain", "id": 8705319}, {"creator": "ntim.bugs@gmail.com", "is_obsolete": 0, "is_patch": 1, "flags": [{"status": "+", "name": "review", "modification_date": "2016-01-07T21:19:44Z", "type_id": 748, "creation_date": "2016-01-07T21:19:44Z", "id": 1319076, "setter": "ntim.bugs@gmail.com"}], "content_type": "text/plain", "id": 8705322}, {"creator": "ntim.bugs@gmail.com", "is_obsolete": 0, "is_patch": 1, "flags": [{"status": "+", "name": "review", "modification_date": "2016-01-07T22:15:07Z", "type_id": 748, "creation_date": "2016-01-07T22:15:07Z", "id": 1319131, "setter": "ntim.bugs@gmail.com"}], "content_type": "text/plain", "id": 8705345}, {"creator": "ntim.bugs@gmail.com", "is_obsolete": 0, "is_patch": 1, "flags": [{"status": "+", "name": "review", "modification_date": "2016-01-19T10:59:16Z", "type_id": 748, "creation_date": "2016-01-17T18:14:56Z", "id": 1325096, "setter": "mratcliffe@mozilla.com"}], "content_type": "text/plain", "id": 8708811}], "classification": "Client Software", "creator": "ev548@xs4all.nl", "cc": ["bgrinstead@mozilla.com", "bugs@pettay.fi", "cbook@mozilla.com", "ev548@xs4all.nl", "jgriffiths@mozilla.com", "jryans@gmail.com", "mratcliffe@mozilla.com", "ntim.bugs@gmail.com", "scrapmachines@gmail.com"], "depends_on": [1181100, 1242832, 1246366, 1285722], "creation_time": "2015-06-05T10:38:20Z", "cf_user_story": "", "cf_tracking_firefox_relnote": "---", "platform": "All", "cf_status_firefox58": "---", "cf_status_firefox59": "---", "keywords": [], "summary": "LocalStorage inspector does not show all key-value pairs", "cf_last_resolved": "2016-02-05T17:09:56Z", "assigned_to_detail": {"email": "ntim.bugs@gmail.com", "id": 445472, "name": "ntim.bugs@gmail.com", "real_name": "Tim Nguyen :ntim"}, "severity": "normal", "is_confirmed": true, "is_creator_accessible": true, "cf_has_regression_range": "---", "assigned_to": "ntim.bugs@gmail.com", "comment_count": 50, "comments": [{"text": "The localStorage inspector only shows a limited number of key-value pairs.\n\nExpected behavior is to show all key-value pairs in a scrollable list.", "author": "ev548@xs4all.nl", "id": 10350045, "time": "2015-06-05T10:38:20Z"}, {"text": "What page are you testing with?", "author": "jryans@gmail.com", "id": 10480603, "time": "2015-07-10T17:56:57Z"}, {"text": "(In reply to J. Ryan Stinnett [:jryans] (use ni?) from comment #1)\n> What page are you testing with?\n\nA web app that I wrote. It stores its internal state in localStorage. There is a publicly accessible installation at\n  https://wwwhome.ewi.utwente.nl/~vriezekolke/Raster/RasterTool/public_group/\nInitially there are few key/value pairs. If you drag a few objects from the templates at the top onto the workspace, the number of pairs increase quickly.", "author": "ev548@xs4all.nl", "id": 10483187, "time": "2015-07-11T20:01:44Z"}, {"text": "The storage tool was heavily reworked in bug 1049888 (Firefox 41) to support e10s.\n\nI believe the issue you are reported is fixed by that work.  However, there is a later, additional issue that prevents the tool from working well in e10s mode (bug 1181100).\n\nSo, let's re-test this once bug 1181100 is resolved.\n\nAlternatively, you could try your site in Firefox 41 or later, but with e10s off.", "author": "jryans@gmail.com", "id": 10487429, "time": "2015-07-13T18:51:42Z"}, {"text": "Tried Firefox 41 (the Developer edition), but with identical & incorrect results.\nI now prepared a minimal test case at \n  http://wwwhome.ewi.utwente.nl/~vriezekolke/test.html.\nThis test case creates 200 localStorage items, but the storage inspector shows only 50.", "author": "ev548@xs4all.nl", "id": 10492733, "time": "2015-07-14T18:04:13Z"}, {"text": "Okay, I can confirm the issue is still present in 42 even after bug 1181100 was fixed.", "author": "jryans@gmail.com", "id": 10574666, "time": "2015-08-04T15:05:55Z"}, {"text": "The actor protocol supports a start index and each query is defaulted to return at max 50 items, unless asked otherwise.\n\nThus this is only a UI limitation i.e. there exists no UI to request next set of items. Alternatively, there is no UI to get X number of items from the actor.", "author": "scrapmachines@gmail.com", "id": 10574681, "time": "2015-08-04T15:10:45Z"}, {"text": "I'm gonna give a try at implementing endless scrolling.", "author": "ntim.bugs@gmail.com", "id": 10600750, "time": "2015-08-10T22:09:42Z"}, {"text": "Created attachment 8646975\nPatch\n\nTested with localStorage.\n\nLet me know if you're OK with the code so I can start writing tests.", "author": "ntim.bugs@gmail.com", "id": 10609451, "time": "2015-08-12T15:40:11Z"}, {"text": "Created attachment 8646976\nPatch", "author": "ntim.bugs@gmail.com", "id": 10609458, "time": "2015-08-12T15:42:27Z"}, {"text": "Created attachment 8647385\nPatch", "author": "ntim.bugs@gmail.com", "id": 10612953, "time": "2015-08-13T08:59:26Z"}, {"text": "Comment on attachment 8647385\nPatch\n\nReview of attachment 8647385:\n-----------------------------------------------------------------\n\nI very much like this, awesome job!", "author": "mratcliffe@mozilla.com", "id": 10618748, "time": "2015-08-14T12:44:03Z"}, {"text": "Don't we need a UI to tell the user that this behavior is even possible?", "author": "scrapmachines@gmail.com", "id": 10618774, "time": "2015-08-14T12:50:19Z"}, {"text": "(In reply to Girish Sharma [:Optimizer] from comment #12)\n> Don't we need a UI to tell the user that this behavior is even possible?\n\nScrolling seems like a natural behaviour to me. When the user scrolls down, he/she expects to see more items.", "author": "ntim.bugs@gmail.com", "id": 10619026, "time": "2015-08-14T13:32:25Z"}, {"text": "Created attachment 8656871\nPatch v1.1 (rebased)\n\nTests coming up this weekend.", "author": "ntim.bugs@gmail.com", "id": 10694694, "time": "2015-09-03T23:07:47Z"}, {"text": "Created attachment 8657630\nTests\n\nPasses fine locally.", "author": "ntim.bugs@gmail.com", "id": 10701172, "time": "2015-09-06T21:59:45Z"}, {"text": "Created attachment 8657631\nPatch v1.2", "author": "ntim.bugs@gmail.com", "id": 10701175, "time": "2015-09-06T22:08:53Z"}, {"text": "Created attachment 8657632\nTests (v1.1)\n\nForgot to hg add the test.", "author": "ntim.bugs@gmail.com", "id": 10701176, "time": "2015-09-06T22:09:57Z"}, {"text": "Try push for both patches : https://treeherder.mozilla.org/#/jobs?repo=try&revision=68d30411abf0", "author": "ntim.bugs@gmail.com", "id": 10701179, "time": "2015-09-06T22:11:30Z"}, {"text": "Comment on attachment 8657631\nPatch v1.2\n\nDidn't mean to make this obsolete.", "author": "ntim.bugs@gmail.com", "id": 10701182, "time": "2015-09-06T22:13:00Z"}, {"text": "Comment on attachment 8657632\nTests (v1.1)\n\nReview of attachment 8657632:\n-----------------------------------------------------------------\n\nAwesome work and a simple test.", "author": "mratcliffe@mozilla.com", "id": 10701602, "time": "2015-09-07T07:13:20Z"}, {"text": "Thanks !", "author": "ntim.bugs@gmail.com", "id": 10702758, "time": "2015-09-07T15:07:50Z"}, {"text": "https://hg.mozilla.org/integration/fx-team/rev/78a423ab972e\nhttps://hg.mozilla.org/integration/fx-team/rev/eb7ef800ed12", "author": "pulsebot@bots.tld", "id": 10703952, "time": "2015-09-08T05:11:55Z"}, {"text": "Backout:\nhttps://hg.mozilla.org/integration/fx-team/rev/d429bacbed6c", "author": "pulsebot@bots.tld", "id": 10704566, "time": "2015-09-08T09:45:46Z"}, {"text": "backed out for test failures like https://treeherder.mozilla.org/logviewer.html#?job_id=4577299&repo=fx-team", "author": "cbook@mozilla.com", "id": 10704636, "time": "2015-09-08T09:58:03Z"}, {"text": "Mike, any chance you can help me fix the test ? The logs don't have any obvious indications of what's going on, and I no longer have much time.", "author": "ntim.bugs@gmail.com", "id": 10717428, "time": "2015-09-10T20:47:51Z"}, {"text": "Sure, I will take over and ping you when I have a patch.", "author": "mratcliffe@mozilla.com", "id": 10719686, "time": "2015-09-11T09:30:20Z"}, {"text": "*** Bug 1237609 has been marked as a duplicate of this bug. ***", "author": "ntim.bugs@gmail.com", "id": 11055947, "time": "2016-01-07T20:13:52Z"}, {"text": "May have a test fix in hand.", "author": "ntim.bugs@gmail.com", "id": 11055960, "time": "2016-01-07T20:18:36Z"}, {"text": "Created attachment 8705319\nPatch v1.3 (rebased)", "author": "ntim.bugs@gmail.com", "id": 11056156, "time": "2016-01-07T21:18:32Z"}, {"text": "Created attachment 8705322\nPart 2 - Test for endless scrolling (v1.2)\n\nrebased as well", "author": "ntim.bugs@gmail.com", "id": 11056162, "time": "2016-01-07T21:19:44Z"}, {"text": "Created attachment 8705345\nPart 1 - Add endless scrolling (v1.4)\n\nforget to qref a change", "author": "ntim.bugs@gmail.com", "id": 11056367, "time": "2016-01-07T22:15:07Z"}, {"text": "Try push: https://treeherder.mozilla.org/#/jobs?repo=try&revision=076517a33340\n\nAlso, Mike, you wanted to review this, so just pinging you so you don't forget.", "author": "ntim.bugs@gmail.com", "id": 11056381, "time": "2016-01-07T22:17:52Z"}, {"text": "(In reply to Tim Nguyen [:ntim] from comment #32)\n> Try push:\n> https://treeherder.mozilla.org/#/jobs?repo=try&revision=076517a33340\nRelevant failure: https://treeherder.mozilla.org/logviewer.html#?job_id=15172944&repo=try\nSeems the test takes too much time on Linux debug for some reason.\n\nThe actual testing in the storage inspector itself (the time between `checking window state` and the test end) takes less than a second. The rest of the test takes 50s to run.\n\nThis seems like a platform problem, not sure what's going on here.\n:smaug, :mayhemer, any idea what's going on here ? (the blame says you touched the DOMStorage code recently, feel free to redirect the request)\n\nIf that helps, here's the relevant code for tests:\nhttps://dxr.mozilla.org/mozilla-central/source/devtools/client/storage/test\nand attachment 8705322.", "author": "ntim.bugs@gmail.com", "id": 11056936, "time": "2016-01-08T00:47:38Z"}, {"text": "Pure guess, but do we end up falling back to non-cached storage somehow and doing plenty of sync IO?\n\n\nCan you reproduce this locally?", "author": "bugs@pettay.fi", "id": 11058495, "time": "2016-01-08T14:42:21Z"}, {"text": "150 items: https://treeherder.mozilla.org/#/jobs?repo=try&revision=7fed6928d821\n100 items: https://treeherder.mozilla.org/#/jobs?repo=try&revision=e737432e37a6\n75 items: https://treeherder.mozilla.org/#/jobs?repo=try&revision=f417b1f92c29\nWithout the useless array (who knows, creating memory slots can take time): https://treeherder.mozilla.org/#/jobs?repo=try&revision=c0954c42a15e", "author": "ntim.bugs@gmail.com", "id": 11059342, "time": "2016-01-08T17:55:12Z"}, {"text": "(In reply to Olli Pettay [:smaug] from comment #34)\n> Pure guess, but do we end up falling back to non-cached storage somehow and\n> doing plenty of sync IO?\n\nActually pretty impossible with the existing implementation.\n\n> \n> \n> Can you reproduce this locally?\n\nI may try.  However:\n\n 15:18:20     INFO -  407 INFO TEST-PASS | devtools/client/storage/test/browser_storage_overflow.js | Table should display all 200 items after scrolling -\n 15:18:20     INFO -  408 INFO Leaving test\n 15:18:20     INFO -  409 INFO TEST-UNEXPECTED-FAIL | devtools/client/storage/test/browser_storage_overflow.js | This test exceeded the timeout threshold. It should be rewritten or split up. If that's not possible, use requestLongerTimeout(N), but only as a last resort. -\n \n\nThe test apparently passes, but hangs at shutdown.  Doesn't seem to be a DOM storage problem IMO..", "author": "honzab.moz@firemni.cz", "id": 11059535, "time": "2016-01-08T18:38:08Z"}, {"text": "Seems like the test triggers a lot of CSS reflows (os something), few stacks like these captured in a debug build while the test apparently hangs and browser eats 100% CPU for a long time:\n\nSample 1:\n\n>\tnss3.dll!_MD_CURRENT_THREAD() Line 312\tC\n \tnss3.dll!PR_GetCurrentThread(...) Line 144\tC\n \txul.dll!nsStandardURL::AddRef() Line 965\tC++\n \txul.dll!nsCOMPtr<nsIURI>::assign_with_AddRef(0x20a96c40) Line 1066\tC++\n \txul.dll!nsCOMPtr<nsIURI>::operator=(0x20a96c40) Line 579\tC++\n \txul.dll!`anonymous namespace'::CSSParserImpl::InitScanner({...}, {...}, 0x20a96c40, 0x20a96c40, 0x1e56d820) Line 1599\tC++\n \txul.dll!`anonymous namespace'::CSSParserImpl::ParsePropertyWithVariableReferences(eCSSProperty_background_clip, eCSSProperty_background, {...}, 0x21d3b1a8, 0x001862c4, 0x20a96c40, 0x20a96c40, 0x1e56d820, 0x00000000, 0x000004fb, 0x000077d7) Line 2877\tC++\n \txul.dll!nsCSSParser::ParsePropertyWithVariableReferences(eCSSProperty_background_clip, eCSSProperty_background, {...}, 0x21d3b1a8, 0x001862c4, 0x20a96c40, 0x20a96c40, 0x1e56d820, 0x00000000, 0x000004fb, 0x000077d7) Line 17267\tC++\n \txul.dll!nsRuleNode::ResolveVariableReferences(nsStyleStructID_Reset_Start, 0x001862c4, 0x221b3940) Line 2235\tC++\n \txul.dll!nsRuleNode::WalkRuleTree(nsStyleStructID_Reset_Start, 0x221b3940) Line 2338\tC++\n \txul.dll!nsRuleNode::GetStyleData(nsStyleStructID_Reset_Start, 0x221b3940, true) Line 9802\tC++\n \txul.dll!nsStyleContext::StyleData(nsStyleStructID_Reset_Start) Line 398\tC++\n \txul.dll!mozilla::StyleAnimationValue::ExtractComputedValue(eCSSProperty_background_color, 0x221b3940, {...}) Line 2991\tC++\n \txul.dll!mozilla::CommonAnimationManager::ExtractComputedValueForTransition(eCSSProperty_background_color, 0x221b3940, {...}) Line 283\tC++\n \txul.dll!nsAnimationManager::BuildSegment({...}, eCSSProperty_background_color, {...}, 0.000000000, 0x22283750, 0x00000000, 1.00000000, 0x221b3940) Line 902\tC++\n \txul.dll!nsAnimationManager::BuildAnimations(0x22283750, 0x22712380, 0x03e2ba00, {...}) Line 849\tC++\n \txul.dll!nsAnimationManager::CheckAnimationRule(0x22283750, 0x22712380) Line 444\tC++\n \txul.dll!nsStyleSet::GetContext(0x22285218, 0x22412280, 0x00000000, 0x00000000, ePseudo_NotPseudoElement, 0x22712380, 0x00000004) Line 977\tC++\n \txul.dll!nsStyleSet::ResolveStyleFor(0x22712380, 0x22285218, {...}) Line 1386\tC++\n \txul.dll!mozilla::ElementRestyler::RestyleSelf(0x224ee9f8, eRestyle_Subtree, 0x00186f44, {...}) Line 4011\tC++\n \txul.dll!mozilla::ElementRestyler::Restyle(eRestyle_Subtree) Line 3287\tC++\n \txul.dll!mozilla::ElementRestyler::ComputeStyleChangeFor(0x224ee9f8, 0x00187294, 0x00000000, {...}, eRestyle_Subtree, {...}, {...}, {...}) Line 4529\tC++\n \txul.dll!mozilla::RestyleManager::ComputeAndProcessStyleChange(0x224ee9f8, 0x00000000, {...}, eRestyle_Subtree, {...}) Line 4940\tC++\n \txul.dll!mozilla::RestyleManager::RestyleElement(0x22712380, 0x224ee9f8, 0x00000000, {...}, eRestyle_Subtree, {...}) Line 1055\tC++\n \txul.dll!mozilla::RestyleTracker::ProcessOneRestyle(0x22712380, eRestyle_Subtree, 0x00000000, {...}) Line 196\tC++\n \txul.dll!mozilla::RestyleTracker::DoProcessRestyles() Line 354\tC++\n \txul.dll!mozilla::RestyleManager::ProcessRestyles({...}) Line 536\tC++\n \txul.dll!mozilla::RestyleManager::ProcessPendingRestyles() Line 1781\tC++\n \txul.dll!PresShell::FlushPendingNotifications({...}) Line 3983\tC++\n \txul.dll!PresShell::FlushPendingNotifications(Flush_Layout) Line 3864\tC++\n \txul.dll!nsDocument::FlushPendingNotifications(Flush_Layout) Line 8145\tC++\n \txul.dll!mozilla::dom::Element::GetPrimaryFrame(Flush_Layout) Line 2122\tC++\n \txul.dll!mozilla::dom::Element::GetStyledFrame() Line 575\tC++\n \txul.dll!nsGenericHTMLElement::GetOffsetRect({...}) Line 331\tC++\n \txul.dll!nsGenericHTMLElement::OffsetWidth() Line 295\tC++\n \txul.dll!mozilla::dom::HTMLElementBinding::get_offsetWidth(0x03e30180, {...}, 0x2226c650, {...}) Line 1586\tC++\n \txul.dll!mozilla::dom::GenericBindingGetter(0x03e30180, 0x00000000, 0x00188760) Line 2648\tC++\n \txul.dll!js::CallJSNative(0x03e30180, 0x0f42dc9c, {...}) Line 235\tC++\n \txul.dll!js::Invoke(0x03e30180, {...}, NO_CONSTRUCT) Line 460\tC++\n \txul.dll!js::Invoke(0x03e30180, {...}, {...}, 0x00000000, 0x00000000, {...}) Line 512\tC++\n \txul.dll!js::InvokeGetter(0x03e30180, {...}, {...}, {...}) Line 621\tC++\n \txul.dll!CallGetter(0x03e30180, {...}, {...}, {...}, {...}) Line 1667\tC++\n \txul.dll!GetExistingProperty<1>(0x03e30180, {...}, {...}, {...}, {...}) Line 1719\tC++\n \txul.dll!NativeGetPropertyInline<1>(0x03e30180, {...}, {...}, {...}, NotNameLookup, {...}) Line 1934\tC++\n \txul.dll!js::NativeGetProperty(0x03e30180, {...}, {...}, {...}, {...}) Line 1968\tC++\n \txul.dll!js::GetProperty(0x03e30180, {...}, {...}, {...}, {...}) Line 1471\tC++\n \txul.dll!js::DirectProxyHandler::get(0x03e30180, {...}, {...}, {...}, {...}) Line 232\tC++\n \txul.dll!js::CrossCompartmentWrapper::get(0x03e30180, {...}, {...}, {...}, {...}) Line 165\tC++\n \txul.dll!xpc::AddonWrapper<js::CrossCompartmentWrapper>::get(0x03e30180, {...}, {...}, {...}, {...}) Line 180\tC++\n \txul.dll!js::Proxy::get(0x03e30180, {...}, {...}, {...}, {...}) Line 300\tC++\n \txul.dll!js::proxy_GetProperty(0x03e30180, {...}, {...}, {...}, {...}) Line 572\tC++\n \txul.dll!js::GetProperty(0x03e30180, {...}, {...}, {...}, {...}) Line 1470\tC++\n \txul.dll!js::GetProperty(0x03e30180, {...}, {...}, 0x0dbc7fc0, {...}) Line 823\tC++\n \txul.dll!js::GetProperty(0x03e30180, {...}, {...}, {...}) Line 4044\tC++\n \txul.dll!js::jit::ComputeGetPropResult(0x03e30180, 0x00188c90, JSOP_GETPROP, {...}, {...}, {...}) Line 2999\tC++\n \txul.dll!js::jit::DoGetPropFallback(0x03e30180, 0x00188c90, 0x081d7758, {...}, {...}) Line 3060\tC++\n\n\nDumpJSStack():\n\n0 Cell.prototype.flash() [\"resource://gre/modules/commonjs/toolkit/loader.js -> resource://devtools/client/shared/widgets/TableWidget.js\":1004]\n    this = [object Object]\n1 Column.prototype.onRowUpdated(event = \"row-updated\", id = \"item-174\") [\"resource://gre/modules/commonjs/toolkit/loader.js -> resource://devtools/client/shared/widgets/TableWidget.js\":610]\n    this = [object Object]\n2 EventEmitter_emit(aEvent = \"row-updated\", \"item-174\") [\"resource://gre/modules/commonjs/toolkit/loader.js -> resource://devtools/shared/event-emitter.js\":147]\n    this = [object Object]\n3 TableWidget.prototype.push(item = [object Object], suppressFlash = false) [\"resource://gre/modules/commonjs/toolkit/loader.js -> resource://devtools/client/shared/widgets/TableWidget.js\":357]\n    this = [object Object]\n4 StorageUI.prototype.populateTable(data = [object Object],[object Object],[object Object],[object Object],[object Object],[object Object],[object Object],[object Object],[object Object],[object Object],[object Object],[object Object],[object Object],[object Object],[object Object],[object Object],[object Object],[object Object],[object Object],[object Object],[object Object],[object Object],[object Object],[object Object],[object Object],[object Object],[object Object],[object Object],[object Object],[object Object],[object Object],[object Object],[object Object],[object Object],[object Object],[object Object],[object Object],[object Object],[object Object],[object Object],[object Object],[object Object],[object Object],[object Object],[object Object],[object Object],[object Object],[object Object],[object Object],[object Object], reason = 3) [\"resource://gre/modules/commonjs/toolkit/loader.js -> resource://devtools/client/storage/ui.js\":602]\n    this = [object Object]\n5 StorageUI.prototype.fetchStorageObjects/<( = [object Object]) [\"resource://gre/modules/commonjs/toolkit/loader.js -> resource://devtools/client/storage/ui.js\":324]\n6 Handler.prototype.process() [\"resource://gre/modules/commonjs/toolkit/loader.js -> resource://gre\n\n\n\n\nSample 2:\n\n>\txul.dll!mozilla::gfx::BaseRect<int,nsRect,nsPoint,nsSize,nsMargin>::BaseRect<int,nsRect,nsPoint,nsSize,nsMargin>(0x00000000, 0x0001caac, 0x000078e8, 0x000005a0) Line 56\tC++\n \txul.dll!nsRect::nsRect(0x00000000, 0x0001caac, 0x000078e8, 0x000005a0) Line 46\tC++\n \txul.dll!nsLeafBoxFrame::Reflow(0x21d47400, {...}, {...}, 0x00000000) Line 301\tC++\n \txul.dll!nsLineLayout::ReflowFrame(0x2124e910, 0x00000000, 0x00000000, false) Line 944\tC++\n \txul.dll!nsBlockFrame::ReflowInlineFrame({...}, {...}, {...}, 0x2124e910, 0x00185624) Line 4053\tC++\n \txul.dll!nsBlockFrame::DoReflowInlineFrames({...}, {...}, {...}, {...}, 0x00000000, 0x00185724, 0x00185926, 0x00185748, true) Line 3887\tC++\n \txul.dll!nsBlockFrame::ReflowInlineFrames({...}, {...}, 0x00185926) Line 3723\tC++\n \txul.dll!nsBlockFrame::ReflowLine({...}, {...}, 0x00185926) Line 2729\tC++\n \txul.dll!nsBlockFrame::ReflowDirtyLines({...}) Line 2264\tC++\n \txul.dll!nsBlockFrame::Reflow(0x21d47400, {...}, {...}, 0x00000000) Line 1180\tC++\n \txul.dll!nsFrame::BoxReflow({...}, 0x21d47400, {...}, 0x001880f8, 0x00000000, 0x00000000, 0x000078e8, 0x000005a0, true) Line 8873\tC++\n \txul.dll!nsFrame::DoLayout({...}) Line 8613\tC++\n \txul.dll!nsIFrame::Layout({...}) Line 511\tC++\n \txul.dll!nsSprocketLayout::Layout(0x078bb7e0, {...}) Line 488\tC++\n \txul.dll!nsBoxFrame::DoLayout({...}) Line 911\tC++\n \txul.dll!nsIFrame::Layout({...}) Line 511\tC++\n \txul.dll!nsSprocketLayout::Layout(0x21d3bfb8, {...}) Line 488\tC++\n \txul.dll!nsBoxFrame::DoLayout({...}) Line 911\tC++\n \txul.dll!nsIFrame::Layout({...}) Line 511\tC++\n \txul.dll!nsXULScrollFrame::LayoutScrollArea({...}, {...}) Line 4409\tC++\n \txul.dll!nsXULScrollFrame::Layout({...}) Line 4600\tC++\n \txul.dll!nsXULScrollFrame::DoLayout({...}) Line 1475\tC++\n \txul.dll!nsIFrame::Layout({...}) Line 511\tC++\n \txul.dll!nsSprocketLayout::Layout(0x21e22880, {...}) Line 488\tC++\n \txul.dll!nsBoxFrame::DoLayout({...}) Line 911\tC++\n \txul.dll!nsIFrame::Layout({...}) Line 511\tC++\n \txul.dll!nsSprocketLayout::Layout(0x21d3b288, {...}) Line 488\tC++\n \txul.dll!nsBoxFrame::DoLayout({...}) Line 911\tC++\n \txul.dll!nsIFrame::Layout({...}) Line 511\tC++\n \txul.dll!nsSprocketLayout::Layout(0x1bb11108, {...}) Line 488\tC++\n \txul.dll!nsBoxFrame::DoLayout({...}) Line 911\tC++\n \txul.dll!nsIFrame::Layout({...}) Line 511\tC++\n \txul.dll!nsStackLayout::Layout(0x1bb10f38, {...}) Line 345\tC++\n \txul.dll!nsBoxFrame::DoLayout({...}) Line 911\tC++\n \txul.dll!nsIFrame::Layout({...}) Line 511\tC++\n \txul.dll!nsBoxFrame::Reflow(0x21d47400, {...}, {...}, 0x00000000) Line 712\tC++\n \txul.dll!nsRootBoxFrame::Reflow(0x21d47400, {...}, {...}, 0x00000000) Line 175\tC++\n \txul.dll!nsContainerFrame::ReflowChild(0x1bb10f38, 0x21d47400, {...}, {...}, 0x00000000, 0x00000000, 0x00000000, 0x00000000, 0x00000000) Line 1037\tC++\n \txul.dll!ViewportFrame::Reflow(0x21d47400, {...}, {...}, 0x00000000) Line 311\tC++\n \txul.dll!PresShell::DoReflow(0x1bb10cc8, false) Line 8886\tC++\n \txul.dll!PresShell::ProcessReflowCommands(false) Line 9053\tC++\n \txul.dll!PresShell::FlushPendingNotifications({...}) Line 4023\tC++\n \txul.dll!PresShell::FlushPendingNotifications(Flush_Layout) Line 3864\tC++\n \txul.dll!nsDocument::FlushPendingNotifications(Flush_Layout) Line 8145\tC++\n \txul.dll!mozilla::dom::Element::GetPrimaryFrame(Flush_Layout) Line 2122\tC++\n \txul.dll!mozilla::dom::Element::GetStyledFrame() Line 575\tC++\n \txul.dll!nsGenericHTMLElement::GetOffsetRect({...}) Line 331\tC++\n \txul.dll!nsGenericHTMLElement::OffsetWidth() Line 295\tC++\n \txul.dll!mozilla::dom::HTMLElementBinding::get_offsetWidth(0x03e30180, {...}, 0x2226c650, {...}) Line 1586\tC++\n \txul.dll!mozilla::dom::GenericBindingGetter(0x03e30180, 0x00000000, 0x00188680) Line 2648\tC++\n \txul.dll!js::CallJSNative(0x03e30180, 0x0f42dc9c, {...}) Line 235\tC++\n \txul.dll!js::Invoke(0x03e30180, {...}, NO_CONSTRUCT) Line 460\tC++\n \txul.dll!js::Invoke(0x03e30180, {...}, {...}, 0x00000000, 0x00000000, {...}) Line 512\tC++\n \txul.dll!js::InvokeGetter(0x03e30180, {...}, {...}, {...}) Line 621\tC++\n \txul.dll!CallGetter(0x03e30180, {...}, {...}, {...}, {...}) Line 1667\tC++\n \txul.dll!GetExistingProperty<1>(0x03e30180, {...}, {...}, {...}, {...}) Line 1719\tC++\n \txul.dll!NativeGetPropertyInline<1>(0x03e30180, {...}, {...}, {...}, NotNameLookup, {...}) Line 1934\tC++\n \txul.dll!js::NativeGetProperty(0x03e30180, {...}, {...}, {...}, {...}) Line 1968\tC++\n \txul.dll!js::GetProperty(0x03e30180, {...}, {...}, {...}, {...}) Line 1471\tC++\n \txul.dll!js::DirectProxyHandler::get(0x03e30180, {...}, {...}, {...}, {...}) Line 232\tC++\n \txul.dll!js::CrossCompartmentWrapper::get(0x03e30180, {...}, {...}, {...}, {...}) Line 165\tC++\n \txul.dll!xpc::AddonWrapper<js::CrossCompartmentWrapper>::get(0x03e30180, {...}, {...}, {...}, {...}) Line 180\tC++\n \txul.dll!js::Proxy::get(0x03e30180, {...}, {...}, {...}, {...}) Line 300\tC++\n \txul.dll!js::proxy_GetProperty(0x03e30180, {...}, {...}, {...}, {...}) Line 572\tC++\n \txul.dll!js::GetProperty(0x03e30180, {...}, {...}, {...}, {...}) Line 1470\tC++\n \txul.dll!js::GetProperty(0x03e30180, {...}, {...}, 0x0dbc7fc0, {...}) Line 823\tC++\n \txul.dll!js::GetProperty(0x03e30180, {...}, {...}, {...}) Line 4044\tC++\n \txul.dll!js::jit::ComputeGetPropResult(0x03e30180, 0x00188bb0, JSOP_GETPROP, {...}, {...}, {...}) Line 2999\tC++\n \txul.dll!js::jit::DoGetPropFallback(0x03e30180, 0x00188bb0, 0x081d7758, {...}, {...}) Line 3060\tC++\n\n\nDumpJSStack():\n\n0 Cell.prototype.flash() [\"resource://gre/modules/commonjs/toolkit/loader.js -> resource://devtools/client/shared/widgets/TableWidget.js\":1004]\n    this = [object Object]\n1 Column.prototype.onRowUpdated(event = \"row-updated\", id = \"item-85\") [\"resource://gre/modules/commonjs/toolkit/loader.js -> resource://devtools/client/shared/widgets/TableWidget.js\":610]\n    this = [object Object]\n2 EventEmitter_emit(aEvent = \"row-updated\", \"item-85\") [\"resource://gre/modules/commonjs/toolkit/loader.js -> resource://devtools/shared/event-emitter.js\":147]\n    this = [object Object]\n3 TableWidget.prototype.push(item = [object Object], suppressFlash = false) [\"resource://gre/modules/commonjs/toolkit/loader.js -> resource://devtools/client/shared/widgets/TableWidget.js\":357]\n    this = [object Object]\n4 StorageUI.prototype.populateTable(data = [object Object],[object Object],[object Object],[object Object],[object Object],[object Object],[object Object],[object Object],[object Object],[object Object],[object Object],[object Object],[object Object],[object Object],[object Object],[object Object],[object Object],[object Object],[object Object],[object Object],[object Object],[object Object],[object Object],[object Object],[object Object],[object Object],[object Object],[object Object],[object Object],[object Object],[object Object],[object Object],[object Object],[object Object],[object Object],[object Object],[object Object],[object Object],[object Object],[object Object],[object Object],[object Object],[object Object],[object Object],[object Object],[object Object],[object Object],[object Object],[object Object],[object Object], reason = 3) [\"resource://gre/modules/commonjs/toolkit/loader.js -> resource://devtools/client/storage/ui.js\":602]\n    this = [object Object]\n5 StorageUI.prototype.fetchStorageObjects/<( = [object Object]) [\"resource://gre/modules/commonjs/toolkit/loader.js -> resource://devtools/client/storage/ui.js\":324]\n6 Handler.prototype.process() [\"resource://gre/modules/commonjs/toolkit/loader.js -> resource://gre/m\n\n\n\nIMO, not a localStorage problem at all...", "author": "honzab.moz@firemni.cz", "id": 11059571, "time": "2016-01-08T18:48:50Z"}, {"text": "(In reply to Honza Bambas (:mayhemer) from comment #37)\n> \n> IMO, not a localStorage problem at all...\nIt seems that :smaug's theory is correct, in comment 35, the try pushes with less localStorage items don't time out.\nMaybe your theory is also correct, I'll test to be sure.", "author": "ntim.bugs@gmail.com", "id": 11060200, "time": "2016-01-08T22:08:40Z"}, {"text": "Nah, given that mayhemer managed to reproduce and got those stack traces even, it clearly shows the test is just doing too much layout-ish stuff.\nDoesn't look like a storage issue.", "author": "bugs@pettay.fi", "id": 11060539, "time": "2016-01-09T00:34:55Z"}, {"text": "(In reply to Olli Pettay [:smaug] from comment #39)\n> Nah, given that mayhemer managed to reproduce and got those stack traces\n> even, it clearly shows the test is just doing too much layout-ish stuff.\n> Doesn't look like a storage issue.\n\nComment 35 probably makes sense as well then, as less layout stuff is being done if you remove items from the table.\n\nWill give a look on how to get rid/do less of these reflows.\n\nThanks for your help, :mayhemer and :smaug !", "author": "ntim.bugs@gmail.com", "id": 11060630, "time": "2016-01-09T01:26:11Z"}, {"text": "Created attachment 8708811\nPart 3 - Disable animations on storage inspector tests and optimise its CSS", "author": "ntim.bugs@gmail.com", "id": 11083131, "time": "2016-01-17T18:14:56Z"}, {"text": "https://treeherder.mozilla.org/#/jobs?repo=try&revision=16bb3a0a89b6", "author": "ntim.bugs@gmail.com", "id": 11083135, "time": "2016-01-17T18:16:58Z"}, {"text": "(In reply to Tim Nguyen [:ntim] from comment #42)\n> https://treeherder.mozilla.org/#/jobs?repo=try&revision=16bb3a0a89b6\n\nThe test now takes 42 seconds to run (and therefore no longer times out) with the CSS animation removed. Although, we might be able to save 10 more seconds by removing ~25-50 items. In the try pushes from comment 35, you can see removing 50 items (with the un-optimized CSS) saves ~15 seconds. Michael, what do you think ?", "author": "ntim.bugs@gmail.com", "id": 11083278, "time": "2016-01-17T20:10:58Z"}, {"text": "It looks great!\n\nLet's land it like this as it should be fine.", "author": "mratcliffe@mozilla.com", "id": 11086821, "time": "2016-01-19T11:01:18Z"}, {"text": "Sounds good !", "author": "ntim.bugs@gmail.com", "id": 11087076, "time": "2016-01-19T13:26:27Z"}, {"text": "https://hg.mozilla.org/integration/fx-team/rev/3e9da0e581c7\nhttps://hg.mozilla.org/integration/fx-team/rev/424bd0dc72e0\nhttps://hg.mozilla.org/integration/fx-team/rev/9331d1f393c2", "author": "pulsebot@bots.tld", "id": 11090720, "time": "2016-01-20T10:07:32Z"}, {"text": "https://hg.mozilla.org/mozilla-central/rev/3e9da0e581c7\nhttps://hg.mozilla.org/mozilla-central/rev/424bd0dc72e0\nhttps://hg.mozilla.org/mozilla-central/rev/9331d1f393c2", "author": "cbook@mozilla.com", "id": 11094587, "time": "2016-01-21T10:53:49Z"}, {"text": "I reported this bug. Unfortunately, after testing I find this solution unsatisfactory. For two reasons:\n\n1. There will be \"gaps\" in the list of keys. E.g. on the specified test URL the key sequence \"key000\" ... \"key199\" will show that some keys are omitted. When scrolling adds more keys to the table those gaps will be filled eventually, but that is not what the user would expect. The correct assumption and normal expectation is that missing key/value pairs are only *below* the current scroll range.\n\n2. When the number of key/value pairs gets larger, scrolling becomes exceedingly slow, leading to hangs of many seconds and \"Unresponsive script\" warnings. This can be experienced when in the test URL the number of keys is increased to 2000. Perhaps the animations should be disabled on scrolling entirely? Animations probably should only occur when keys are added or values are changed, not when more keys come into view.", "author": "ev548@xs4all.nl", "id": 11140993, "time": "2016-02-05T13:43:15Z"}, {"text": "(In reply to ev548 from comment #48)\n> I reported this bug. Unfortunately, after testing I find this solution\n> unsatisfactory. For two reasons:\n> \n> 1. There will be \"gaps\" in the list of keys. E.g. on the specified test URL\n> the key sequence \"key000\" ... \"key199\" will show that some keys are omitted.\n> When scrolling adds more keys to the table those gaps will be filled\n> eventually, but that is not what the user would expect. The correct\n> assumption and normal expectation is that missing key/value pairs are only\n> *below* the current scroll range.\n> \n> 2. When the number of key/value pairs gets larger, scrolling becomes\n> exceedingly slow, leading to hangs of many seconds and \"Unresponsive script\"\n> warnings. This can be experienced when in the test URL the number of keys is\n> increased to 2000. Perhaps the animations should be disabled on scrolling\n> entirely? Animations probably should only occur when keys are added or\n> values are changed, not when more keys come into view.\nThese are indeed issues, but the root issue of this bug has been fixed. Please file new bugs.", "author": "ntim.bugs@gmail.com", "id": 11141832, "time": "2016-02-05T17:09:56Z"}], "id": 1171903, "priority": "P2", "mentors_detail": [], "cf_crash_signature": "", "version": "unspecified", "cf_qa_whiteboard": "", "cf_tracking_firefox_esr52": "---", "cf_tracking_firefox59": "---", "last_change_time": "2016-07-09T08:41:42Z", "cf_platform_rel": "---", "product": "Firefox", "cf_status_firefox_esr52": "---", "blocks": [1194190], "qa_contact": "", "see_also": ["https://bugzilla.mozilla.org/show_bug.cgi?id=1246371"], "cf_fx_iteration": "---", "component": "Developer Tools: Storage Inspector", "votes": 0, "groups": [], "cf_status_firefox60": "---", "target_milestone": "Firefox 46", "is_cc_accessible": true, "cf_status_firefox46": "fixed", "url": "https://wwwhome.ewi.utwente.nl/~vriezekolke/test.html", "creator_detail": {"email": "ev548@xs4all.nl", "id": 428267, "name": "ev548@xs4all.nl", "real_name": ""}, "whiteboard": "[polish-backlog]", "mentors": [], "cc_detail": [{"email": "bgrinstead@mozilla.com", "id": 476442, "name": "bgrinstead@mozilla.com", "real_name": "Brian Grinstead [:bgrins]"}, {"email": "bugs@pettay.fi", "id": 39966, "name": "bugs@pettay.fi", "real_name": "Olli Pettay [:smaug]"}, {"email": "cbook@mozilla.com", "id": 277293, "name": "cbook@mozilla.com", "real_name": "Carsten Book [:Tomcat]"}, {"email": "ev548@xs4all.nl", "id": 428267, "name": "ev548@xs4all.nl", "real_name": ""}, {"email": "jgriffiths@mozilla.com", "id": 421111, "name": "jgriffiths@mozilla.com", "real_name": "Jeff Griffiths (:canuckistani) (:\u26a1\ufe0e)"}, {"email": "jryans@gmail.com", "id": 282978, "name": "jryans@gmail.com", "real_name": "J. Ryan Stinnett [:jryans] (use ni?)"}, {"email": "mratcliffe@mozilla.com", "id": 313697, "name": "mratcliffe@mozilla.com", "real_name": "Mike Ratcliffe [:miker] [:mratcliffe] [:mikeratcliffe]"}, {"email": "ntim.bugs@gmail.com", "id": 445472, "name": "ntim.bugs@gmail.com", "real_name": "Tim Nguyen :ntim"}, {"email": "scrapmachines@gmail.com", "id": 405947, "name": "scrapmachines@gmail.com", "real_name": "Girish Sharma [:Optimizer]"}], "cf_has_str": "---", "alias": null, "dupe_of": null, "flags": [], "cf_tracking_firefox58": "---", "cf_rank": null, "is_open": false, "resolution": "FIXED", "op_sys": "All", "cf_fx_points": "---", "history": [{"changes": [{"removed": "", "field_name": "cc", "added": "ev548@xs4all.nl"}], "who": "ev548@xs4all.nl", "when": "2015-06-05T10:38:45Z"}, {"changes": [{"removed": "", "field_name": "cc", "added": "jryans@gmail.com"}, {"removed": "", "field_name": "flagtypes.name", "added": "needinfo?(ev548@xs4all.nl)"}], "who": "jryans@gmail.com", "when": "2015-07-10T17:56:57Z"}, {"changes": [{"removed": "", "field_name": "url", "added": "https://wwwhome.ewi.utwente.nl/~vriezekolke/Raster/RasterTool/public_group/"}, {"removed": "needinfo?(ev548@xs4all.nl)", "field_name": "flagtypes.name", "added": ""}], "who": "ev548@xs4all.nl", "when": "2015-07-11T20:02:49Z"}, {"changes": [{"removed": "", "field_name": "depends_on", "added": "1181100"}], "who": "jryans@gmail.com", "when": "2015-07-13T18:51:42Z"}, {"changes": [{"removed": "https://wwwhome.ewi.utwente.nl/~vriezekolke/Raster/RasterTool/public_group/", "field_name": "url", "added": "https://wwwhome.ewi.utwente.nl/~vriezekolke/test.html"}], "who": "ev548@xs4all.nl", "when": "2015-07-14T18:04:13Z"}, {"changes": [{"removed": "UNCONFIRMED", "field_name": "status", "added": "NEW"}, {"removed": "0", "field_name": "is_confirmed", "added": "1"}, {"removed": "", "field_name": "whiteboard", "added": "[polish-backlog]"}], "who": "jryans@gmail.com", "when": "2015-08-04T15:05:55Z"}, {"changes": [{"removed": "", "field_name": "cc", "added": "scrapmachines@gmail.com"}], "who": "scrapmachines@gmail.com", "when": "2015-08-04T15:10:45Z"}, {"changes": [{"removed": "NEW", "field_name": "status", "added": "ASSIGNED"}, {"removed": "", "field_name": "cc", "added": "ntim.bugs@gmail.com"}, {"removed": "nobody@mozilla.org", "field_name": "assigned_to", "added": "ntim.bugs@gmail.com"}], "who": "ntim.bugs@gmail.com", "when": "2015-08-10T22:09:42Z"}, {"changes": [{"removed": "", "field_name": "cc", "added": "mratcliffe@mozilla.com"}, {"field_name": "flagtypes.name", "removed": "", "attachment_id": 8646975, "added": "review?(mratcliffe@mozilla.com)"}], "who": "ntim.bugs@gmail.com", "when": "2015-08-12T15:40:11Z"}, {"changes": [{"field_name": "attachments.isobsolete", "removed": "0", "attachment_id": 8646975, "added": "1"}, {"field_name": "flagtypes.name", "removed": "review?(mratcliffe@mozilla.com)", "attachment_id": 8646975, "added": ""}, {"field_name": "flagtypes.name", "removed": "", "attachment_id": 8646976, "added": "review?(mratcliffe@mozilla.com)"}], "who": "ntim.bugs@gmail.com", "when": "2015-08-12T15:42:27Z"}, {"changes": [{"field_name": "attachments.isobsolete", "removed": "0", "attachment_id": 8646976, "added": "1"}, {"field_name": "flagtypes.name", "removed": "review?(mratcliffe@mozilla.com)", "attachment_id": 8646976, "added": ""}, {"field_name": "flagtypes.name", "removed": "", "attachment_id": 8647385, "added": "review?(mratcliffe@mozilla.com)"}], "who": "ntim.bugs@gmail.com", "when": "2015-08-13T08:59:26Z"}, {"changes": [{"removed": "", "field_name": "depends_on", "added": "1194190"}], "who": "ntim.bugs@gmail.com", "when": "2015-08-13T12:10:31Z"}, {"changes": [{"removed": "", "field_name": "blocks", "added": "1194190"}, {"removed": "1194190", "field_name": "depends_on", "added": ""}], "who": "ntim.bugs@gmail.com", "when": "2015-08-13T12:19:40Z"}, {"changes": [{"field_name": "flagtypes.name", "removed": "review?(mratcliffe@mozilla.com)", "attachment_id": 8647385, "added": "review+"}], "who": "mratcliffe@mozilla.com", "when": "2015-08-14T12:44:03Z"}, {"changes": [{"field_name": "attachments.isobsolete", "removed": "0", "attachment_id": 8647385, "added": "1"}, {"field_name": "flagtypes.name", "removed": "", "attachment_id": 8656871, "added": "review+"}], "who": "ntim.bugs@gmail.com", "when": "2015-09-03T23:07:47Z"}, {"changes": [{"field_name": "flagtypes.name", "removed": "", "attachment_id": 8657630, "added": "review?(mratcliffe@mozilla.com)"}], "who": "ntim.bugs@gmail.com", "when": "2015-09-06T21:59:45Z"}, {"changes": [{"field_name": "attachments.isobsolete", "removed": "0", "attachment_id": 8656871, "added": "1"}, {"field_name": "attachments.isobsolete", "removed": "0", "attachment_id": 8657630, "added": "1"}, {"field_name": "flagtypes.name", "removed": "review?(mratcliffe@mozilla.com)", "attachment_id": 8657630, "added": ""}, {"field_name": "flagtypes.name", "removed": "", "attachment_id": 8657631, "added": "review+"}], "who": "ntim.bugs@gmail.com", "when": "2015-09-06T22:08:53Z"}, {"changes": [{"field_name": "attachments.isobsolete", "removed": "0", "attachment_id": 8657631, "added": "1"}, {"field_name": "flagtypes.name", "removed": "", "attachment_id": 8657632, "added": "review?(mratcliffe@mozilla.com)"}], "who": "ntim.bugs@gmail.com", "when": "2015-09-06T22:09:57Z"}, {"changes": [{"field_name": "attachments.isobsolete", "removed": "1", "attachment_id": 8657631, "added": "0"}], "who": "ntim.bugs@gmail.com", "when": "2015-09-06T22:13:00Z"}, {"changes": [{"field_name": "flagtypes.name", "removed": "review?(mratcliffe@mozilla.com)", "attachment_id": 8657632, "added": "review+"}], "who": "mratcliffe@mozilla.com", "when": "2015-09-07T07:13:20Z"}, {"changes": [{"removed": "", "field_name": "keywords", "added": "checkin-needed"}], "who": "ntim.bugs@gmail.com", "when": "2015-09-07T15:07:50Z"}, {"changes": [{"removed": "checkin-needed", "field_name": "keywords", "added": ""}], "who": "pulsebot@bots.tld", "when": "2015-09-08T05:11:55Z"}, {"changes": [{"removed": "", "field_name": "cc", "added": "cbook@mozilla.com"}], "who": "cbook@mozilla.com", "when": "2015-09-08T09:58:03Z"}, {"changes": [{"removed": "", "field_name": "flagtypes.name", "added": "needinfo?(mratcliffe@mozilla.com)"}], "who": "ntim.bugs@gmail.com", "when": "2015-09-10T20:47:51Z"}, {"changes": [{"removed": "ntim.bugs@gmail.com", "field_name": "assigned_to", "added": "mratcliffe@mozilla.com"}, {"removed": "needinfo?(mratcliffe@mozilla.com)", "field_name": "flagtypes.name", "added": ""}], "who": "mratcliffe@mozilla.com", "when": "2015-09-11T09:30:20Z"}, {"changes": [{"removed": "--", "field_name": "priority", "added": "P2"}, {"removed": "", "field_name": "cc", "added": "jgriffiths@mozilla.com"}], "who": "jgriffiths@mozilla.com", "when": "2015-09-24T23:50:35Z"}, {"changes": [{"removed": "mratcliffe@mozilla.com", "field_name": "assigned_to", "added": "ntim.bugs@gmail.com"}], "who": "ntim.bugs@gmail.com", "when": "2016-01-07T20:18:36Z"}, {"changes": [{"field_name": "attachments.isobsolete", "removed": "0", "attachment_id": 8657631, "added": "1"}, {"field_name": "attachments.isobsolete", "removed": "0", "attachment_id": 8657632, "added": "1"}, {"field_name": "flagtypes.name", "removed": "", "attachment_id": 8705319, "added": "review+"}], "who": "ntim.bugs@gmail.com", "when": "2016-01-07T21:18:32Z"}, {"changes": [{"field_name": "flagtypes.name", "removed": "", "attachment_id": 8705322, "added": "review+"}], "who": "ntim.bugs@gmail.com", "when": "2016-01-07T21:19:44Z"}, {"changes": [{"field_name": "attachments.isobsolete", "removed": "0", "attachment_id": 8705319, "added": "1"}, {"field_name": "flagtypes.name", "removed": "", "attachment_id": 8705345, "added": "review+"}], "who": "ntim.bugs@gmail.com", "when": "2016-01-07T22:15:07Z"}, {"changes": [{"removed": "", "field_name": "flagtypes.name", "added": "needinfo?(mratcliffe@mozilla.com)"}], "who": "ntim.bugs@gmail.com", "when": "2016-01-07T22:17:52Z"}, {"changes": [{"removed": "", "field_name": "cc", "added": "bugs@pettay.fi, honzab.moz@firemni.cz"}, {"removed": "", "field_name": "flagtypes.name", "added": "needinfo?(honzab.moz@firemni.cz), needinfo?(bugs@pettay.fi)"}], "who": "ntim.bugs@gmail.com", "when": "2016-01-08T00:47:38Z"}, {"changes": [{"removed": "needinfo?(bugs@pettay.fi)", "field_name": "flagtypes.name", "added": ""}], "who": "bugs@pettay.fi", "when": "2016-01-08T14:42:21Z"}, {"changes": [{"removed": "needinfo?(honzab.moz@firemni.cz)", "field_name": "flagtypes.name", "added": ""}], "who": "honzab.moz@firemni.cz", "when": "2016-01-08T18:48:50Z"}, {"changes": [{"removed": "", "field_name": "cc", "added": "bgrinstead@mozilla.com"}], "who": "bgrinstead@mozilla.com", "when": "2016-01-08T21:58:42Z"}, {"changes": [{"removed": "honzab.moz@firemni.cz", "field_name": "cc", "added": ""}], "who": "honzab.moz@firemni.cz", "when": "2016-01-11T12:20:11Z"}, {"changes": [{"field_name": "flagtypes.name", "removed": "", "attachment_id": 8708811, "added": "review?(mratcliffe@mozilla.com)"}], "who": "ntim.bugs@gmail.com", "when": "2016-01-17T18:14:56Z"}, {"changes": [{"field_name": "attachments.description", "removed": "Patch v1.4 (land before tests)", "attachment_id": 8705345, "added": "Part 1 - Add endless scrolling (v1.4)"}], "who": "ntim.bugs@gmail.com", "when": "2016-01-17T18:15:29Z"}, {"changes": [{"field_name": "attachments.description", "removed": "Tests v1.2", "attachment_id": 8705322, "added": "Part 2 - Test for endless scrolling (v1.2)"}], "who": "ntim.bugs@gmail.com", "when": "2016-01-17T18:15:57Z"}, {"changes": [{"field_name": "flagtypes.name", "removed": "review?(mratcliffe@mozilla.com)", "attachment_id": 8708811, "added": "review+"}], "who": "mratcliffe@mozilla.com", "when": "2016-01-19T10:59:16Z"}, {"changes": [{"removed": "needinfo?(mratcliffe@mozilla.com)", "field_name": "flagtypes.name", "added": "needinfo?(ntim.bugs@gmail.com)"}], "who": "mratcliffe@mozilla.com", "when": "2016-01-19T11:01:18Z"}, {"changes": [{"removed": "", "field_name": "keywords", "added": "checkin-needed"}, {"removed": "needinfo?(ntim.bugs@gmail.com)", "field_name": "flagtypes.name", "added": ""}], "who": "ntim.bugs@gmail.com", "when": "2016-01-19T13:26:27Z"}, {"changes": [{"removed": "checkin-needed", "field_name": "keywords", "added": ""}], "who": "pulsebot@bots.tld", "when": "2016-01-20T10:07:32Z"}, {"changes": [{"removed": "ASSIGNED", "field_name": "status", "added": "RESOLVED"}, {"removed": "", "field_name": "resolution", "added": "FIXED"}, {"removed": "---", "field_name": "target_milestone", "added": "Firefox 46"}, {"removed": "", "field_name": "cf_last_resolved", "added": "2016-01-21 02:53:49"}, {"removed": "---", "field_name": "cf_status_firefox46", "added": "fixed"}], "who": "cbook@mozilla.com", "when": "2016-01-21T10:53:49Z"}, {"changes": [{"removed": "RESOLVED", "field_name": "status", "added": "REOPENED"}, {"removed": "FIXED", "field_name": "resolution", "added": ""}], "who": "ev548@xs4all.nl", "when": "2016-02-05T13:43:51Z"}, {"changes": [{"removed": "REOPENED", "field_name": "status", "added": "RESOLVED"}, {"removed": "", "field_name": "resolution", "added": "FIXED"}, {"removed": "2016-01-21 02:53:49", "field_name": "cf_last_resolved", "added": "2016-02-05 09:09:56"}], "who": "ntim.bugs@gmail.com", "when": "2016-02-05T17:09:56Z"}, {"changes": [{"removed": "", "field_name": "depends_on", "added": "1246366"}], "who": "yfdyh000@gmail.com", "when": "2016-02-06T07:55:32Z"}, {"changes": [{"removed": "", "field_name": "see_also", "added": "https://bugzilla.mozilla.org/show_bug.cgi?id=1246371"}], "who": "yfdyh000@gmail.com", "when": "2016-02-06T08:30:04Z"}, {"changes": [{"removed": "", "field_name": "depends_on", "added": "1242832"}], "who": "ntim.bugs@gmail.com", "when": "2016-02-27T15:13:58Z"}, {"changes": [{"removed": "", "field_name": "depends_on", "added": "1285722"}], "who": "aryx.bugmail@gmx-topmail.de", "when": "2016-07-09T08:41:42Z"}]}