{"cf_tracking_thunderbird_esr52": "---", "status": "NEW", "cf_tracking_firefox60": "---", "cf_tracking_firefox61": "---", "cf_tracking_firefox62": "---", "creator": "intermittent-bug-filer@mozilla.bugs", "mentors_detail": [], "depends_on": [1441563, 1443803], "cf_status_firefox_esr60": "---", "cf_user_story": "", "cf_backlog": "---", "cf_tracking_firefox_relnote": "---", "platform": "Unspecified", "cf_status_firefox59": "---", "keywords": ["intermittent-failure", "leave-open"], "cc_detail": [{"email": "apavel@mozilla.com", "id": 600553, "name": "apavel@mozilla.com", "real_name": "Andreea Pavel [:apavel]"}, {"email": "dminor@mozilla.com", "id": 466787, "name": "dminor@mozilla.com", "real_name": "Dan Minor [:dminor]"}, {"email": "docfaraday@gmail.com", "id": 478411, "name": "docfaraday@gmail.com", "real_name": "Byron Campen [:bwc]"}, {"email": "jmaher@mozilla.com", "id": 324370, "name": "jmaher@mozilla.com", "real_name": "Joel Maher ( :jmaher ) (UTC-4)"}, {"email": "jorendorff@mozilla.com", "id": 281791, "name": "jorendorff@mozilla.com", "real_name": "Jason Orendorff [:jorendorff]"}], "cf_last_resolved": null, "attachments": [{"creator": "aiakab@mozilla.com", "is_obsolete": 0, "is_patch": 1, "flags": [{"status": "+", "name": "review", "modification_date": "2018-03-12T11:09:50Z", "type_id": 4, "creation_date": "2018-03-12T04:41:03Z", "id": 1728167, "setter": "jmaher@mozilla.com"}], "content_type": "text/plain", "id": 8958021}, {"creator": "aiakab@mozilla.com", "is_obsolete": 0, "is_patch": 1, "flags": [{"status": "+", "name": "review", "modification_date": "2018-03-14T13:48:35Z", "type_id": 4, "creation_date": "2018-03-14T13:46:35Z", "id": 1729449, "setter": "jmaher@mozilla.com"}], "content_type": "text/plain", "id": 8958813}], "votes": 0, "classification": "Components", "is_confirmed": true, "is_creator_accessible": true, "cf_has_regression_range": "---", "comment_count": 31, "comments": [{"text": "Filed by: apavel [at] mozilla.com\n\nhttps://treeherder.mozilla.org/logviewer.html#?job_id=157607000&repo=autoland\n\nhttps://queue.taskcluster.net/v1/task/eAt8CottSLONb78jAISAFg/runs/0/artifacts/public/logs/live_backing.log\n\n[task 2018-01-21T11:54:53.473Z] 11:54:53     INFO - Call getUserMedia for {\"audio\":{\"autoGainControl\":false,\"echoCancellation\":false,\"noiseSuppression\":false},\"video\":true}\n[task 2018-01-21T11:54:53.474Z] 11:54:53     INFO - Buffered messages logged at 11:48:27\n[task 2018-01-21T11:54:53.475Z] 11:54:53     INFO - TEST-PASS | dom/media/tests/mochitest/test_peerConnection_transceivers.html | One audio track shall be present \n[task 2018-01-21T11:54:53.476Z] 11:54:53     INFO - TEST-PASS | dom/media/tests/mochitest/test_peerConnection_transceivers.html | Track kind should be audio \n[task 2018-01-21T11:54:53.477Z] 11:54:53     INFO - TEST-PASS | dom/media/tests/mochitest/test_peerConnection_transceivers.html | Track id should be defined \n[task 2018-01-21T11:54:53.478Z] 11:54:53     INFO - TEST-PASS | dom/media/tests/mochitest/test_peerConnection_transceivers.html | Track should not be muted \n[task 2018-01-21T11:54:53.479Z] 11:54:53     INFO - TEST-PASS | dom/media/tests/mochitest/test_peerConnection_transceivers.html | One video track shall be present \n[task 2018-01-21T11:54:53.480Z] 11:54:53     INFO - TEST-PASS | dom/media/tests/mochitest/test_peerConnection_transceivers.html | Track kind should be video \n[task 2018-01-21T11:54:53.481Z] 11:54:53     INFO - TEST-PASS | dom/media/tests/mochitest/test_peerConnection_transceivers.html | Track id should be defined \n[task 2018-01-21T11:54:53.482Z] 11:54:53     INFO - TEST-PASS | dom/media/tests/mochitest/test_peerConnection_transceivers.html | Track should not be muted \n[task 2018-01-21T11:54:53.483Z] 11:54:53     INFO - Waiting for ICE connected...\n[task 2018-01-21T11:54:53.484Z] 11:54:53     INFO - Adding ICE candidate: {\"candidate\":\"candidate:0 1 UDP 2122252543 172.17.0.4 36323 typ host\",\"sdpMid\":\"sdparta_0\",\"sdpMLineIndex\":0}\n[task 2018-01-21T11:54:53.485Z] 11:54:53     INFO - Adding ICE candidate: {\"candidate\":\"candidate:1 1 TCP 2105524479 172.17.0.4 9 typ host tcptype active\",\"sdpMid\":\"sdparta_0\",\"sdpMLineIndex\":0}\n[task 2018-01-21T11:54:53.486Z] 11:54:53     INFO - Adding ICE candidate: {\"candidate\":\"candidate:0 2 UDP 2122252542 172.17.0.4 50431 typ host\",\"sdpMid\":\"sdparta_0\",\"sdpMLineIndex\":0}\n[task 2018-01-21T11:54:53.487Z] 11:54:53     INFO - Adding ICE candidate: {\"candidate\":\"candidate:1 2 TCP 2105524478 172.17.0.4 9 typ host tcptype active\",\"sdpMid\":\"sdparta_0\",\"sdpMLineIndex\":0}\n[task 2018-01-21T11:54:53.488Z] 11:54:53     INFO - Adding ICE candidate: null\n[task 2018-01-21T11:54:53.489Z] 11:54:53     INFO - Adding ICE candidate: {\"candidate\":\"candidate:0 1 UDP 2122252543 172.17.0.4 53959 typ host\",\"sdpMid\":\"sdparta_0\",\"sdpMLineIndex\":0}\n[task 2018-01-21T11:54:53.490Z] 11:54:53     INFO - Adding ICE candidate: {\"candidate\":\"candidate:1 1 TCP 2105524479 172.17.0.4 9 typ host tcptype active\",\"sdpMid\":\"sdparta_0\",\"sdpMLineIndex\":0}\n[task 2018-01-21T11:54:53.491Z] 11:54:53     INFO - Buffered messages logged at 11:48:28\n[task 2018-01-21T11:54:53.491Z] 11:54:53     INFO - Adding ICE candidate: null\n[task 2018-01-21T11:54:53.493Z] 11:54:53     INFO - TEST-PASS | dom/media/tests/mochitest/test_peerConnection_transceivers.html | ICE connected \n[task 2018-01-21T11:54:53.494Z] 11:54:53     INFO - Waiting for ICE connected...\n[task 2018-01-21T11:54:53.495Z] 11:54:53     INFO - TEST-PASS | dom/media/tests/mochitest/test_peerConnection_transceivers.html | ICE connected \n[task 2018-01-21T11:54:53.495Z] 11:54:53     INFO - TEST-PASS | dom/media/tests/mochitest/test_peerConnection_transceivers.html | track should not be muted after onunmute \n[task 2018-01-21T11:54:53.496Z] 11:54:53     INFO - TEST-PASS | dom/media/tests/mochitest/test_peerConnection_transceivers.html | track should not be muted after onunmute \n[task 2018-01-21T11:54:53.497Z] 11:54:53     INFO - TEST-PASS | dom/media/tests/mochitest/test_peerConnection_transceivers.html | track should not be muted after onunmute \n[task 2018-01-21T11:54:53.498Z] 11:54:53     INFO - TEST-PASS | dom/media/tests/mochitest/test_peerConnection_transceivers.html | track should not be muted after onunmute \n[task 2018-01-21T11:54:53.499Z] 11:54:53     INFO - TEST-PASS | dom/media/tests/mochitest/test_peerConnection_transceivers.html | track should be muted after onmute \n[task 2018-01-21T11:54:53.500Z] 11:54:53     INFO - TEST-PASS | dom/media/tests/mochitest/test_peerConnection_transceivers.html | track should be muted after onmute \n[task 2018-01-21T11:54:53.501Z] 11:54:53     INFO - TEST-PASS | dom/media/tests/mochitest/test_peerConnection_transceivers.html | track should be muted after onmute \n[task 2018-01-21T11:54:53.502Z] 11:54:53     INFO - TEST-PASS | dom/media/tests/mochitest/test_peerConnection_transceivers.html | track should be muted after onmute \n[task 2018-01-21T11:54:53.503Z] 11:54:53     INFO - TEST-PASS | dom/media/tests/mochitest/test_peerConnection_transceivers.html | track should not be muted after onunmute \n[task 2018-01-21T11:54:53.504Z] 11:54:53     INFO - TEST-PASS | dom/media/tests/mochitest/test_peerConnection_transceivers.html | track should not be muted after onunmute \n[task 2018-01-21T11:54:53.505Z] 11:54:53     INFO - Adding ICE candidate: null\n[task 2018-01-21T11:54:53.506Z] 11:54:53     INFO - Adding ICE candidate: null\n[task 2018-01-21T11:54:53.507Z] 11:54:53     INFO - Adding ICE candidate: null\n[task 2018-01-21T11:54:53.508Z] 11:54:53     INFO - Adding ICE candidate: null\n[task 2018-01-21T11:54:53.509Z] 11:54:53     INFO - Adding ICE candidate: null\n[task 2018-01-21T11:54:53.509Z] 11:54:53     INFO - Buffered messages logged at 11:48:29\n[task 2018-01-21T11:54:53.510Z] 11:54:53     INFO - Adding ICE candidate: null\n[task 2018-01-21T11:54:53.511Z] 11:54:53     INFO - TEST-PASS | dom/media/tests/mochitest/test_peerConnection_transceivers.html | track should not be muted after onunmute \n[task 2018-01-21T11:54:53.512Z] 11:54:53     INFO - TEST-PASS | dom/media/tests/mochitest/test_peerConnection_transceivers.html | track should not be muted after onunmute \n[task 2018-01-21T11:54:53.513Z] 11:54:53     INFO - TEST-FAIL | dom/media/tests/mochitest/test_peerConnection_transceivers.html | The author of the test has indicated that flaky timeouts are expected.  Reason: WebRTC inherently depends on timeouts \n[task 2018-01-21T11:54:53.514Z] 11:54:53     INFO - Buffered messages finished\n[task 2018-01-21T11:54:53.515Z] 11:54:53    ERROR - TEST-UNEXPECTED-TIMEOUT | dom/media/tests/mochitest/test_peerConnection_transceivers.html | application timed out after 370 seconds with no output\n[task 2018-01-21T11:54:53.516Z] 11:54:53    ERROR - Force-terminating active process(es).\n[task 2018-01-21T11:54:53.517Z] 11:54:53     INFO - Determining child pids from psutil...\n[task 2018-01-21T11:54:53.518Z] 11:54:53     INFO - [3261]\n[task 2018-01-21T11:54:53.519Z] 11:54:53     INFO - ==> process 3159 launched child process 3182\n[task 2018-01-21T11:54:53.520Z] 11:54:53     INFO - ==> process 3159 launched child process 3210\n[task 2018-01-21T11:54:53.521Z] 11:54:53     INFO - ==> process 3159 launched child process 3261\n[task 2018-01-21T11:54:53.522Z] 11:54:53     INFO - ==> process 3159 launched child process 4158\n[task 2018-01-21T11:54:53.523Z] 11:54:53     INFO - ==> process 3159 launched child process 4578\n[task 2018-01-21T11:54:53.523Z] 11:54:53     INFO - ==> process 3159 launched child process 5019\n[task 2018-01-21T11:54:53.524Z] 11:54:53     INFO - ==> process 3159 launched child process 5497\n[task 2018-01-21T11:54:53.526Z] 11:54:53     INFO - Found child pids: set([4578, 3210, 3182, 5497, 5019, 3261, 4158])\n[task 2018-01-21T11:54:53.527Z] 11:54:53     INFO - Failed to get child procs\n[task 2018-01-21T11:54:53.528Z] 11:54:53     INFO - Killing process: 4578\n[task 2018-01-21T11:54:53.529Z] 11:54:53     INFO - TEST-INFO | started process screentopng\n[task 2018-01-21T11:54:53.682Z] 11:54:53     INFO - TEST-INFO | screentopng: exit 0\n[task 2018-01-21T11:54:53.683Z] 11:54:53     INFO - Can't trigger Breakpad, process no longer exists\n[task 2018-01-21T11:54:53.685Z] 11:54:53     INFO - Killing process: 3210\n[task 2018-01-21T11:54:53.689Z] 11:54:53     INFO - Not taking screenshot here: see the one that was previously logged\n[task 2018-01-21T11:54:53.690Z] 11:54:53     INFO - Can't trigger Breakpad, process no longer exists\n[task 2018-01-21T11:54:53.691Z] 11:54:53     INFO - Killing process: 3182\n[task 2018-01-21T11:54:53.692Z] 11:54:53     INFO - Not taking screenshot here: see the one that was previously logged\n[task 2018-01-21T11:54:53.693Z] 11:54:53     INFO - Can't trigger Breakpad, process no longer exists\n[task 2018-01-21T11:54:53.694Z] 11:54:53     INFO - Killing process: 5497\n[task 2018-01-21T11:54:53.695Z] 11:54:53     INFO - Not taking screenshot here: see the one that was previously logged\n[task 2018-01-21T11:54:53.696Z] 11:54:53     INFO - Can't trigger Breakpad, process no longer exists\n[task 2018-01-21T11:54:53.697Z] 11:54:53     INFO - Killing process: 5019\n[task 2018-01-21T11:54:53.698Z] 11:54:53     INFO - Not taking screenshot here: see the one that was previously logged\n[task 2018-01-21T11:54:53.699Z] 11:54:53     INFO - Can't trigger Breakpad, process no longer exists\n[task 2018-01-21T11:54:53.700Z] 11:54:53     INFO - Killing process: 3261\n[task 2018-01-21T11:54:53.701Z] 11:54:53     INFO - Not taking screenshot here: see the one that was previously logged\n[task 2018-01-21T11:54:53.702Z] 11:54:53     INFO - Killing process: 4158\n[task 2018-01-21T11:54:53.704Z] 11:54:53     INFO - Not taking screenshot here: see the one that was previously logged\n[task 2018-01-21T11:54:53.705Z] 11:54:53     INFO - Can't trigger Breakpad, process no longer exists\n[task 2018-01-21T11:54:53.707Z] 11:54:53     INFO - Killing process: 3159\n[task 2018-01-21T11:54:53.709Z] 11:54:53     INFO - Not taking screenshot here: see the one that was previously logged\n[task 2018-01-21T11:54:53.935Z] 11:54:53     INFO - psutil found pid 3159 dead\n[task 2018-01-21T11:54:54.085Z] 11:54:54  WARNING - runtests.py | Failed to get app exit code - running/crashed?\n[task 2018-01-21T11:54:54.087Z] 11:54:54     INFO - TEST-INFO | Main app process: exit 0\n[task 2018-01-21T11:54:54.088Z] 11:54:54     INFO - runtests.py | Application ran for: 0:19:39.144087\n[task 2018-01-21T11:54:54.089Z] 11:54:54     INFO - zombiecheck | Reading PID log: /tmp/tmpXa3Ftqpidlog\n[task 2018-01-21T11:54:54.091Z] 11:54:54     INFO - ==> process 3159 launched child process 3182\n[task 2018-01-21T11:54:54.093Z] 11:54:54     INFO - ==> process 3159 launched child process 3210\n[task 2018-01-21T11:54:54.093Z] 11:54:54     INFO - ==> process 3159 launched child process 3261\n[task 2018-01-21T11:54:54.094Z] 11:54:54     INFO - ==> process 3159 launched child process 4158\n[task 2018-01-21T11:54:54.094Z] 11:54:54     INFO - ==> process 3159 launched child process 4578\n[task 2018-01-21T11:54:54.094Z] 11:54:54     INFO - ==> process 3159 launched child process 5019\n[task 2018-01-21T11:54:54.095Z] 11:54:54     INFO - ==> process 3159 launched child process 5497\n[task 2018-01-21T11:54:54.095Z] 11:54:54     INFO - zombiecheck | Checking for orphan process with PID: 4578\n[task 2018-01-21T11:54:54.095Z] 11:54:54     INFO - zombiecheck | Checking for orphan process with PID: 3210\n[task 2018-01-21T11:54:54.095Z] 11:54:54     INFO - zombiecheck | Checking for orphan process with PID: 3182\n[task 2018-01-21T11:54:54.096Z] 11:54:54     INFO - zombiecheck | Checking for orphan process with PID: 5497\n[task 2018-01-21T11:54:54.096Z] 11:54:54     INFO - zombiecheck | Checking for orphan process with PID: 5019\n[task 2018-01-21T11:54:54.096Z] 11:54:54     INFO - zombiecheck | Checking for orphan process with PID: 3261\n[task 2018-01-21T11:54:54.097Z] 11:54:54     INFO - zombiecheck | Checking for orphan process with PID: 4158\n[task 2018-01-21T11:54:54.097Z] 11:54:54     INFO - mozcrash Copy/paste: /usr/local/bin/linux64-minidump_stackwalk /tmp/tmpUOcupg.mozrunner/minidumps/55c6f926-fa54-cd5e-cafd-00056bb7794e.dmp /builds/worker/workspace/build/symbols\n[task 2018-01-21T11:55:03.102Z] 11:55:03     INFO - mozcrash Saved minidump as /builds/worker/workspace/build/blobber_upload_dir/55c6f926-fa54-cd5e-cafd-00056bb7794e.dmp\n[task 2018-01-21T11:55:03.103Z] 11:55:03     INFO - mozcrash Saved app info as /builds/worker/workspace/build/blobber_upload_dir/55c6f926-fa54-cd5e-cafd-00056bb7794e.extra\n[task 2018-01-21T11:55:03.165Z] 11:55:03     INFO - PROCESS-CRASH | Main app process exited normally | application crashed [@ linux-gate.so + 0xcd9]\n[task 2018-01-21T11:55:03.166Z] 11:55:03     INFO - Crash dump filename: /tmp/tmpUOcupg.mozrunner/minidumps/55c6f926-fa54-cd5e-cafd-00056bb7794e.dmp\n[task 2018-01-21T11:55:03.167Z] 11:55:03     INFO - Operating system: Linux\n[task 2018-01-21T11:55:03.168Z] 11:55:03     INFO -                   0.0.0 Linux 4.4.0-98-generic #121~14.04.1-Ubuntu SMP Wed Oct 11 11:54:55 UTC 2017 x86_64\n[task 2018-01-21T11:55:03.168Z] 11:55:03     INFO - CPU: x86\n[task 2018-01-21T11:55:03.169Z] 11:55:03     INFO -      GenuineIntel family 6 model 62 stepping 4\n[task 2018-01-21T11:55:03.170Z] 11:55:03     INFO -      2 CPUs\n[task 2018-01-21T11:55:03.171Z] 11:55:03     INFO - \n[task 2018-01-21T11:55:03.172Z] 11:55:03     INFO - GPU: UNKNOWN\n[task 2018-01-21T11:55:03.173Z] 11:55:03     INFO - \n[task 2018-01-21T11:55:03.174Z] 11:55:03     INFO - Crash reason:  SIGABRT\n[task 2018-01-21T11:55:03.175Z] 11:55:03     INFO - Crash address: 0x3c6\n[task 2018-01-21T11:55:03.176Z] 11:55:03     INFO - Process uptime: not available\n[task 2018-01-21T11:55:03.177Z] 11:55:03     INFO - \n[task 2018-01-21T11:55:03.177Z] 11:55:03     INFO - Thread 0 (crashed)\n[task 2018-01-21T11:55:03.179Z] 11:55:03     INFO -  0  linux-gate.so + 0xcd9\n[task 2018-01-21T11:55:03.180Z] 11:55:03     INFO -     eip = 0xf76ffcd9   esp = 0xff922a84   ebp = 0xff922af8   ebx = 0xe42c3aa0\n[task 2018-01-21T11:55:03.181Z] 11:55:03     INFO -     esi = 0xf71437b0   edi = 0xe42c3aa0   eax = 0xfffffffc   ecx = 0x00000004\n[task 2018-01-21T11:55:03.182Z] 11:55:03     INFO -     edx = 0xffffffff   efl = 0x00000296\n[task 2018-01-21T11:55:03.183Z] 11:55:03     INFO -     Found by: given as instruction pointer in context\n[task 2018-01-21T11:55:03.183Z] 11:55:03     INFO -  1  libglib-2.0.so.0.4800.2 + 0x4711c\n[task 2018-01-21T11:55:03.184Z] 11:55:03     INFO -     eip = 0xf5da811c   esp = 0xff922b00   ebp = 0x00000004\n[task 2018-01-21T11:55:03.185Z] 11:55:03     INFO -     Found by: previous frame's frame pointer\n[task 2018-01-21T11:55:03.186Z] 11:55:03     INFO -  2  libglib-2.0.so.0.4800.2 + 0x8cfec\n[task 2018-01-21T11:55:03.187Z] 11:55:03     INFO -     eip = 0xf5dedfec   esp = 0xff922b10   ebp = 0x00000004\n[task 2018-01-21T11:55:03.188Z] 11:55:03     INFO -     Found by: stack scanning\n[task 2018-01-21T11:55:03.189Z] 11:55:03     INFO -  3  libxul.so!IsFrameContentNodeInNamespace [nsNativeThemeGTK.cpp:9fe69ff0762d : 115 + 0x4]\n[task 2018-01-21T11:55:03.190Z] 11:55:03     INFO -     eip = 0xf131a943   esp = 0xff922b14   ebp = 0x00000004\n[task 2018-01-21T11:55:03.190Z] 11:55:03     INFO -     Found by: stack scanning\n[task 2018-01-21T11:55:03.191Z] 11:55:03     INFO -  4  libglib-2.0.so.0.4800.2 + 0x1285b0\n[task 2018-01-21T11:55:03.192Z] 11:55:03     INFO -     eip = 0xf5e895b0   esp = 0xff922b24   ebp = 0x00000004\n[task 2018-01-21T11:55:03.193Z] 11:55:03     INFO -     Found by: stack scanning\n[task 2018-01-21T11:55:03.194Z] 11:55:03     INFO -  5  libglib-2.0.so.0.4800.2 + 0x46f8d\n[task 2018-01-21T11:55:03.195Z] 11:55:03     INFO -     eip = 0xf5da7f8d   esp = 0xff922b3c   ebp = 0xff922b58\n[task 2018-01-21T11:55:03.196Z] 11:55:03     INFO -     Found by: stack scanning", "author": "intermittent-bug-filer@mozilla.bugs", "id": 12983883, "time": "2018-01-21T14:26:32Z"}, {"text": "1 failures in 657 pushes (0.002 failures/push) were associated with this bug in the last 7 days.    \n\nRepository breakdown:\n* autoland: 1\n\nPlatform breakdown:\n* linux32: 1\n\nFor more details, see:\nhttps://brasstacks.mozilla.com/orangefactor/?display=Bug&bugid=1432025&startday=2018-01-15&endday=2018-01-21&tree=all", "author": "orangefactor@bots.tld", "id": 12985022, "time": "2018-01-22T01:28:51Z"}, {"text": "9 failures in 701 pushes (0.013 failures/push) were associated with this bug in the last 7 days.    \n\nRepository breakdown:\n* mozilla-inbound: 3\n* autoland: 3\n* try: 2\n* mozilla-central: 1\n\nPlatform breakdown:\n* linux64-qr: 4\n* linux64: 2\n* linux32: 2\n* linux32-stylo-disabled: 1\n\nFor more details, see:\nhttps://brasstacks.mozilla.com/orangefactor/?display=Bug&bugid=1432025&startday=2018-01-22&endday=2018-01-28&tree=all", "author": "orangefactor@bots.tld", "id": 13001073, "time": "2018-01-29T01:28:10Z"}, {"text": "5 failures in 735 pushes (0.007 failures/push) were associated with this bug in the last 7 days.    \n\nRepository breakdown:\n* mozilla-inbound: 2\n* mozilla-central: 2\n* try: 1\n\nPlatform breakdown:\n* linux64-stylo-disabled: 2\n* linux32-stylo-disabled: 2\n* linux64: 1\n\nFor more details, see:\nhttps://brasstacks.mozilla.com/orangefactor/?display=Bug&bugid=1432025&startday=2018-01-29&endday=2018-02-04&tree=all", "author": "orangefactor@bots.tld", "id": 13017691, "time": "2018-02-05T01:29:34Z"}, {"text": "5 failures in 702 pushes (0.007 failures/push) were associated with this bug in the last 7 days.    \n\nRepository breakdown:\n* autoland: 4\n* try: 1\n\nPlatform breakdown:\n* linux32: 3\n* linux64: 2\n\nFor more details, see:\nhttps://brasstacks.mozilla.com/orangefactor/?display=Bug&bugid=1432025&startday=2018-02-05&endday=2018-02-11&tree=all", "author": "orangefactor@bots.tld", "id": 13034622, "time": "2018-02-12T01:27:53Z"}, {"text": "5 failures in 685 pushes (0.007 failures/push) were associated with this bug in the last 7 days.    \n\nRepository breakdown:\n* mozilla-inbound: 2\n* autoland: 2\n* mozilla-central: 1\n\nPlatform breakdown:\n* linux32: 3\n* linux32-stylo-disabled: 2\n\nFor more details, see:\nhttps://brasstacks.mozilla.com/orangefactor/?display=Bug&bugid=1432025&startday=2018-02-12&endday=2018-02-18&tree=all", "author": "orangefactor@bots.tld", "id": 13051459, "time": "2018-02-19T01:27:27Z"}, {"text": "8 failures in 675 pushes (0.012 failures/push) were associated with this bug in the last 7 days.    \n\nRepository breakdown:\n* mozilla-central: 4\n* mozilla-inbound: 3\n* autoland: 1\n\nPlatform breakdown:\n* windows10-64: 4\n* linux64: 2\n* linux64-stylo-disabled: 1\n* linux32: 1\n\nFor more details, see:\nhttps://brasstacks.mozilla.com/orangefactor/?display=Bug&bugid=1432025&startday=2018-02-19&endday=2018-02-25&tree=all", "author": "orangefactor@bots.tld", "id": 13067871, "time": "2018-02-26T01:29:31Z"}, {"text": "17 failures in 831 pushes (0.02 failures/push) were associated with this bug in the last 7 days.    \n\nRepository breakdown:\n* autoland: 6\n* mozilla-central: 4\n* mozilla-inbound: 3\n* try: 2\n* mozilla-beta: 2\n\nPlatform breakdown:\n* linux64-qr: 11\n* windows10-64-nightly: 3\n* windows10-64: 3\n\nFor more details, see:\nhttps://brasstacks.mozilla.com/orangefactor/?display=Bug&bugid=1432025&startday=2018-02-26&endday=2018-03-04&tree=all", "author": "orangefactor@bots.tld", "id": 13102431, "time": "2018-03-05T01:35:49Z"}, {"text": "26 failures in 116 pushes (0.224 failures/push) were associated with this bug yesterday.    \n\nRepository breakdown:\n* autoland: 17\n* mozilla-central: 4\n* mozilla-inbound: 3\n* try: 2\n\nPlatform breakdown:\n* linux64-qr: 21\n* linux32: 4\n* linux32-stylo-disabled: 1\n\nFor more details, see:\nhttps://brasstacks.mozilla.com/orangefactor/?display=Bug&bugid=1432025&startday=2018-03-06&endday=2018-03-06&tree=all", "author": "orangefactor@bots.tld", "id": 13109907, "time": "2018-03-07T01:01:06Z"}, {"text": "This has gotten extremely bad sometime around the 1st or 2nd.\n\nI see lots of failures like the following:\n\n[task 2018-03-03T16:32:19.138Z] 16:32:19     INFO - PROCESS-CRASH | Main app process exited normally | application crashed [@ mozilla::Atomic<bool, (mozilla::MemoryOrdering)2u, void>::operator bool]", "author": "docfaraday@gmail.com", "id": 13111026, "time": "2018-03-07T14:51:48Z"}, {"text": "33 failures in 160 pushes (0.206 failures/push) were associated with this bug yesterday.    \n\nRepository breakdown:\n* autoland: 16\n* mozilla-inbound: 12\n* mozilla-central: 3\n* try: 2\n\nPlatform breakdown:\n* linux64-qr: 17\n* linux32: 8\n* linux32-stylo-disabled: 7\n* linux64: 1\n\nFor more details, see:\nhttps://brasstacks.mozilla.com/orangefactor/?display=Bug&bugid=1432025&startday=2018-03-07&endday=2018-03-07&tree=all", "author": "orangefactor@bots.tld", "id": 13112978, "time": "2018-03-08T01:01:20Z"}, {"text": "Seems permanently orange for me on Linux x64 QuantumRender debug:  https://treeherder.mozilla.org/#/jobs?repo=try&revision=b1dbb3f07cc7311b186e642aa8a8e1774088f8a6&selectedJob=166630581\n\nLogs show PROCESS-CRASH messages like the one in comment 9.\n\nResetting the priority to get this reconsidered -- something has changed.", "author": "jorendorff@mozilla.com", "id": 13114225, "time": "2018-03-08T16:00:50Z"}, {"text": "Raising priority. Byron has been looking at intermittent failures lately and is active on this bug, but I'll leave a needinfo just in case :)", "author": "dminor@mozilla.com", "id": 13115243, "time": "2018-03-08T21:26:20Z"}, {"text": "Bug 1443803 seems to be a regression due to bug 1440040 according to pehrsons. I am looking into it right now, but this is deep in unfamiliar code for me.", "author": "docfaraday@gmail.com", "id": 13115251, "time": "2018-03-08T21:29:41Z"}, {"text": "27 failures in 126 pushes (0.214 failures/push) were associated with this bug yesterday.    \n\nRepository breakdown:\n* autoland: 17\n* mozilla-inbound: 4\n* try: 3\n* mozilla-central: 3\n\nPlatform breakdown:\n* linux64-qr: 18\n* linux32: 5\n* linux32-stylo-disabled: 4\n\nFor more details, see:\nhttps://brasstacks.mozilla.com/orangefactor/?display=Bug&bugid=1432025&startday=2018-03-08&endday=2018-03-08&tree=all", "author": "orangefactor@bots.tld", "id": 13115765, "time": "2018-03-09T01:00:57Z"}, {"text": "*** Bug 1444305 has been marked as a duplicate of this bug. ***", "author": "aryx.bugmail@gmx-topmail.de", "id": 13116357, "time": "2018-03-09T10:02:40Z"}, {"text": "21 failures in 145 pushes (0.145 failures/push) were associated with this bug yesterday.    \n\n** This test has failed more than 150 times in the last 21 days. It should be disabled until it can be fixed. ** \n\nRepository breakdown:\n* mozilla-inbound: 9\n* autoland: 6\n* try: 5\n* mozilla-central: 1\n\nPlatform breakdown:\n* linux64-qr: 15\n* linux32-stylo-disabled: 4\n* linux32: 2\n\nFor more details, see:\nhttps://brasstacks.mozilla.com/orangefactor/?display=Bug&bugid=1432025&startday=2018-03-09&endday=2018-03-09&tree=all", "author": "orangefactor@bots.tld", "id": 13118459, "time": "2018-03-10T01:01:08Z"}, {"text": "15 failures in 45 pushes (0.333 failures/push) were associated with this bug yesterday.    \n\nRepository breakdown:\n* mozilla-inbound: 6\n* autoland: 5\n* try: 3\n* mozilla-central: 1\n\nPlatform breakdown:\n* linux64-qr: 11\n* linux32-stylo-disabled: 2\n* linux64-stylo-disabled: 1\n* linux32: 1\n\nFor more details, see:\nhttps://brasstacks.mozilla.com/orangefactor/?display=Bug&bugid=1432025&startday=2018-03-10&endday=2018-03-10&tree=all", "author": "orangefactor@bots.tld", "id": 13119280, "time": "2018-03-11T01:00:39Z"}, {"text": "147 failures in 747 pushes (0.197 failures/push) were associated with this bug in the last 7 days. \n\nThis is the #4 most frequent failure this week. \n\n** This failure happened more than 75 times this week! Resolving this bug is a very high priority. **\n\n** Try to resolve this bug as soon as possible. If unresolved for 1 week, the affected test(s) may be disabled. **   \n\nRepository breakdown:\n* autoland: 71\n* mozilla-inbound: 43\n* try: 18\n* mozilla-central: 15\n\nPlatform breakdown:\n* linux64-qr: 101\n* linux32: 24\n* linux32-stylo-disabled: 18\n* linux64-stylo-disabled: 3\n* windows10-64: 1\n\nFor more details, see:\nhttps://brasstacks.mozilla.com/orangefactor/?display=Bug&bugid=1432025&startday=2018-03-05&endday=2018-03-11&tree=all", "author": "orangefactor@bots.tld", "id": 13120725, "time": "2018-03-12T01:35:17Z"}, {"text": "Created attachment 8958021\nDisabled on Linux jsdcov platform\n\nCreated a disable patch in case it is needed.", "author": "aiakab@mozilla.com", "id": 13121233, "time": "2018-03-12T04:41:03Z"}, {"text": "Comment on attachment 8958021\nDisabled on Linux jsdcov platform\n\nReview of attachment 8958021:\n-----------------------------------------------------------------\n\nplease adjust the comment, this says | on Linux jsdcov platform|, and it should be | on Linux debug platform|", "author": "jmaher@mozilla.com", "id": 13121712, "time": "2018-03-12T11:09:50Z"}, {"text": "27 failures in 132 pushes (0.205 failures/push) were associated with this bug yesterday.    \n\nRepository breakdown:\n* autoland: 12\n* mozilla-inbound: 7\n* mozilla-central: 5\n* try: 3\n\nPlatform breakdown:\n* linux64-qr: 19\n* linux32-stylo-disabled: 4\n* linux64-stylo-disabled: 2\n* linux32: 2\n\nFor more details, see:\nhttps://brasstacks.mozilla.com/orangefactor/?display=Bug&bugid=1432025&startday=2018-03-12&endday=2018-03-12&tree=all", "author": "orangefactor@bots.tld", "id": 13123952, "time": "2018-03-13T01:01:06Z"}, {"text": "35 failures in 171 pushes (0.205 failures/push) were associated with this bug yesterday.    \n\nRepository breakdown:\n* mozilla-inbound: 17\n* autoland: 13\n* mozilla-central: 5\n\nPlatform breakdown:\n* linux64-qr: 14\n* linux32-stylo-disabled: 14\n* linux32: 7\n\nFor more details, see:\nhttps://brasstacks.mozilla.com/orangefactor/?display=Bug&bugid=1432025&startday=2018-03-13&endday=2018-03-13&tree=all", "author": "orangefactor@bots.tld", "id": 13126931, "time": "2018-03-14T01:01:08Z"}, {"text": "Created attachment 8958813\nDisabling on Linux debug platform\n\nUpdated the patch, corrected the message.", "author": "aiakab@mozilla.com", "id": 13127804, "time": "2018-03-14T13:46:35Z"}, {"text": "Pushed by aiakab@mozilla.com:\nhttps://hg.mozilla.org/integration/mozilla-inbound/rev/700bfd08642d\ndisabling test_peerConnection_transceivers.html on Linux debug platform r=jmaher", "author": "pulsebot@bots.tld", "id": 13128257, "time": "2018-03-14T16:37:30Z"}, {"text": "https://hg.mozilla.org/mozilla-central/rev/700bfd08642d", "author": "apavel@mozilla.com", "id": 13129377, "time": "2018-03-14T22:14:10Z"}, {"text": "18 failures in 141 pushes (0.128 failures/push) were associated with this bug yesterday.    \n\nRepository breakdown:\n* autoland: 9\n* try: 5\n* mozilla-inbound: 2\n* mozilla-central: 2\n\nPlatform breakdown:\n* linux64-qr: 14\n* linux32-stylo-disabled: 2\n* linux32: 2\n\nFor more details, see:\nhttps://brasstacks.mozilla.com/orangefactor/?display=Bug&bugid=1432025&startday=2018-03-14&endday=2018-03-14&tree=all", "author": "orangefactor@bots.tld", "id": 13129747, "time": "2018-03-15T01:01:01Z"}, {"text": "84 failures in 814 pushes (0.103 failures/push) were associated with this bug in the last 7 days. \n\nThis is the #12 most frequent failure this week. \n\n** This failure happened more than 75 times this week! Resolving this bug is a very high priority. **\n\n** Try to resolve this bug as soon as possible. If unresolved for 1 week, the affected test(s) may be disabled. **   \n\nRepository breakdown:\n* autoland: 34\n* mozilla-inbound: 26\n* mozilla-central: 13\n* try: 10\n* mozilla-beta: 1\n\nPlatform breakdown:\n* linux64-qr: 50\n* linux32-stylo-disabled: 21\n* linux32: 11\n* linux64-stylo-disabled: 2\n\nFor more details, see:\nhttps://brasstacks.mozilla.com/orangefactor/?display=Bug&bugid=1432025&startday=2018-03-12&endday=2018-03-18&tree=all", "author": "orangefactor@bots.tld", "id": 13138154, "time": "2018-03-19T01:57:02Z"}, {"text": "1 failures in 822 pushes (0.001 failures/push) were associated with this bug in the last 7 days.    \n\nRepository breakdown:\n* mozilla-release: 1\n\nPlatform breakdown:\n* linux32: 1\n\nFor more details, see:\nhttps://treeherder.mozilla.org/intermittent-failures.html#/bugdetails?bug=1432025&startday=2018-03-20&endday=2018-03-26&tree=trunk", "author": "orangefactor@bots.tld", "id": 13160271, "time": "2018-03-27T17:35:22Z"}, {"text": "1 failures in 718 pushes (0.001 failures/push) were associated with this bug in the last 7 days.    \n\nRepository breakdown:\n* mozilla-release: 1\n\nPlatform breakdown:\n* linux32: 1\n\nFor more details, see:\nhttps://treeherder.mozilla.org/intermittent-failures.html#/bugdetails?bug=1432025&startday=2018-03-26&endday=2018-04-01&tree=trunk", "author": "orangefactor@bots.tld", "id": 13172400, "time": "2018-04-02T01:25:56Z"}, {"text": "1 failures in 780 pushes (0.001 failures/push) were associated with this bug in the last 7 days.    \n\nRepository breakdown:\n* mozilla-release: 1\n\nPlatform breakdown:\n* linux32: 1\n\nFor more details, see:\nhttps://treeherder.mozilla.org/intermittent-failures.html#/bugdetails?bug=1432025&startday=2018-04-23&endday=2018-04-29&tree=trunk", "author": "orangefactor@bots.tld", "id": 13241506, "time": "2018-04-30T01:26:33Z"}], "id": 1432025, "priority": "P2", "cc": ["apavel@mozilla.com", "dminor@mozilla.com", "docfaraday@gmail.com", "jmaher@mozilla.com", "jorendorff@mozilla.com"], "cf_crash_signature": "", "version": "unspecified", "is_cc_accessible": true, "cf_tracking_firefox_esr52": "---", "see_also": [], "cf_tracking_firefox59": "---", "cf_tracking_thunderbird_esr60": "---", "cf_platform_rel": "---", "product": "Core", "cf_fx_iteration": "---", "blocks": [], "qa_contact": "", "creation_time": "2018-01-21T14:26:32Z", "cf_status_firefox_esr52": "---", "component": "WebRTC", "assigned_to_detail": {"email": "aiakab@mozilla.com", "id": 600605, "name": "aiakab@mozilla.com", "real_name": "Arthur Iakab [arthur_iakab]"}, "cf_tracking_firefox_esr60": "---", "cf_status_firefox62": "---", "cf_status_firefox61": "---", "cf_status_firefox60": "---", "target_milestone": "---", "cf_rank": "15", "cf_qa_whiteboard": "", "severity": "normal", "groups": [], "cf_status_thunderbird_esr52": "---", "url": "", "cf_status_thunderbird_esr60": "---", "creator_detail": {"email": "intermittent-bug-filer@mozilla.bugs", "id": 573381, "name": "intermittent-bug-filer@mozilla.bugs", "real_name": "Treeherder Bug Filer"}, "whiteboard": "[stockwell disabled]", "mentors": [], "summary": "Intermittent TEST-UNEXPECTED-TIMEOUT | dom/media/tests/mochitest/test_peerConnection_transceivers.html | application timed out after 370 seconds with no output", "cf_has_str": "---", "alias": null, "dupe_of": null, "flags": [], "last_change_time": "2018-04-30T01:26:33Z", "assigned_to": "aiakab@mozilla.com", "is_open": true, "history": [{"changes": [{"removed": "", "field_name": "cc", "added": "apavel@mozilla.com"}], "who": "apavel@mozilla.com", "when": "2018-01-21T14:27:19Z"}, {"changes": [{"removed": "", "field_name": "depends_on", "added": "1441563"}], "who": "docfaraday@gmail.com", "when": "2018-02-27T15:55:21Z"}, {"changes": [{"removed": "", "field_name": "cc", "added": "docfaraday@gmail.com"}], "who": "docfaraday@gmail.com", "when": "2018-03-07T14:51:48Z"}, {"changes": [{"removed": "", "field_name": "depends_on", "added": "1443803"}], "who": "docfaraday@gmail.com", "when": "2018-03-07T14:54:07Z"}, {"changes": [{"removed": "P5", "field_name": "priority", "added": "--"}, {"removed": "", "field_name": "cc", "added": "jorendorff@mozilla.com"}], "who": "jorendorff@mozilla.com", "when": "2018-03-08T16:00:50Z"}, {"changes": [{"removed": "", "field_name": "cf_rank", "added": "15"}, {"removed": "--", "field_name": "priority", "added": "P2"}, {"removed": "", "field_name": "cc", "added": "dminor@mozilla.com"}, {"removed": "", "field_name": "flagtypes.name", "added": "needinfo?(docfaraday@gmail.com)"}], "who": "dminor@mozilla.com", "when": "2018-03-08T21:26:20Z"}, {"changes": [{"removed": "needinfo?(docfaraday@gmail.com)", "field_name": "flagtypes.name", "added": ""}], "who": "docfaraday@gmail.com", "when": "2018-03-08T21:29:41Z"}, {"changes": [{"removed": "", "field_name": "whiteboard", "added": "[stockwell disable-recommended]"}], "who": "orangefactor@bots.tld", "when": "2018-03-10T01:01:08Z"}, {"changes": [{"removed": "", "field_name": "cc", "added": "jmaher@mozilla.com"}, {"removed": "nobody@mozilla.org", "field_name": "assigned_to", "added": "aiakab@mozilla.com"}, {"field_name": "flagtypes.name", "removed": "", "attachment_id": 8958021, "added": "review?(jmaher@mozilla.com)"}], "who": "aiakab@mozilla.com", "when": "2018-03-12T04:41:03Z"}, {"changes": [{"field_name": "flagtypes.name", "removed": "review?(jmaher@mozilla.com)", "attachment_id": 8958021, "added": "review+"}], "who": "jmaher@mozilla.com", "when": "2018-03-12T11:09:50Z"}, {"changes": [{"field_name": "flagtypes.name", "removed": "", "attachment_id": 8958813, "added": "review?(jmaher@mozilla.com)"}], "who": "aiakab@mozilla.com", "when": "2018-03-14T13:46:35Z"}, {"changes": [{"field_name": "flagtypes.name", "removed": "review?(jmaher@mozilla.com)", "attachment_id": 8958813, "added": "review+"}], "who": "jmaher@mozilla.com", "when": "2018-03-14T13:48:35Z"}, {"changes": [{"removed": "", "field_name": "keywords", "added": "checkin-needed, leave-open"}], "who": "jmaher@mozilla.com", "when": "2018-03-14T13:48:50Z"}, {"changes": [{"removed": "checkin-needed", "field_name": "keywords", "added": ""}], "who": "pulsebot@bots.tld", "when": "2018-03-14T16:37:30Z"}, {"changes": [{"removed": "[stockwell disable-recommended]", "field_name": "whiteboard", "added": "[stockwell disabled]"}], "who": "nbeleuzu@mozilla.com", "when": "2018-03-16T19:25:57Z"}], "resolution": "", "op_sys": "Unspecified", "cf_fx_points": "---", "cf_blocking_fennec": "---"}