{"status": "NEW", "cf_tracking_firefox60": "---", "cf_tracking_firefox61": "---", "classification": "Client Software", "creator": "dholbert@mozilla.com", "cc": ["dao+bmo@mozilla.com", "florian@queze.net", "sledru@mozilla.com"], "depends_on": [], "creation_time": "2018-05-16T21:08:51Z", "cf_user_story": "", "cf_tracking_firefox_relnote": "---", "platform": "Unspecified", "keywords": ["regression"], "summary": "In Private Browsing mode, a ctrl+clicked \"javascript:\" link produces a blank tab with purple background (rather than white)", "cf_last_resolved": null, "attachments": [{"creator": "dholbert@mozilla.com", "is_obsolete": 0, "is_patch": 0, "flags": [], "content_type": "video/ogg", "id": 8976337}, {"creator": "dholbert@mozilla.com", "is_obsolete": 0, "is_patch": 0, "flags": [], "content_type": "text/html", "id": 8976340}], "assigned_to_detail": {"email": "nobody@mozilla.org", "id": 1, "name": "nobody@mozilla.org", "real_name": "Nobody; OK to take it and work on it"}, "severity": "normal", "is_confirmed": true, "is_creator_accessible": true, "cf_has_regression_range": "---", "comment_count": 5, "comments": [{"text": "STR:\n 1. Open a private browsing window and visit a page with a javascript link, like data:text/html,<a href='javascript:'>OHAI\n\nFor example, you could run the following on the command line to do this in a fresh profile /tmp/foo (in Linux at least):\n  mkdir /tmp/foo\n  firefox -no-remote -profile /tmp/foo \\\n    -private-window \"data:text/html,<a href='javascript:'>OHAI\"\n\n2. Ctrl-click the link to open a new tab.\n\nEXPECTED RESULTS:\nThe new tab should have a white background.\n\nACTUAL RESULTS:\nThe new tab has a purple background.\n\nRegression range:\nhttps://hg.mozilla.org/integration/mozilla-inbound/pushloghtml?fromchange=f89ae3c450ce33915e4d2fff0b11b942dec17f1a&tochange=0e14317d2f6c454e86549fe84d6067e1745a76c5\n\n--> regression from bug 1379587", "author": "dholbert@mozilla.com", "id": 13282777, "time": "2018-05-16T21:08:51Z"}, {"text": "Created attachment 8976337\nscreencast of bug", "author": "dholbert@mozilla.com", "id": 13282780, "time": "2018-05-16T21:10:12Z"}, {"text": "Created attachment 8976340\ntestcase", "author": "dholbert@mozilla.com", "id": 13282818, "time": "2018-05-16T21:19:55Z"}, {"text": "Note that an explicitly-visited \"about:blank\" page has a *white* background (including in private browsing mode).\n\nI think this bug's STR should produce those same results -- white background in the new tab. There are no other steps I'm aware of that produce a blank tab with a purple background, so when this happens, it feels quite odd/unexpected.", "author": "dholbert@mozilla.com", "id": 13282823, "time": "2018-05-16T21:23:11Z"}, {"text": "There's also bug 1422507 that produces a similar result.", "author": "florian@queze.net", "id": 13385264, "time": "2018-06-04T14:29:31Z"}], "id": 1462131, "priority": "P3", "mentors_detail": [], "cf_crash_signature": "", "version": "unspecified", "cf_qa_whiteboard": "", "cf_tracking_firefox_esr52": "---", "cf_tracking_firefox62": "---", "cf_platform_rel": "---", "product": "Firefox", "cf_status_firefox_esr52": "---", "blocks": [1379587], "qa_contact": "", "see_also": [], "cf_fx_iteration": "---", "component": "Tabbed Browser", "votes": 0, "cf_tracking_firefox_esr60": "---", "cf_status_firefox62": "---", "cf_status_firefox61": "---", "cf_status_firefox60": "---", "target_milestone": "---", "is_cc_accessible": true, "cf_rank": null, "groups": [], "url": "", "creator_detail": {"email": "dholbert@mozilla.com", "id": 278074, "name": "dholbert@mozilla.com", "real_name": "Daniel Holbert [:dholbert]"}, "whiteboard": "", "mentors": [], "cc_detail": [{"email": "dao+bmo@mozilla.com", "id": 219124, "name": "dao+bmo@mozilla.com", "real_name": "D\u00e3o Gottwald [::dao]"}, {"email": "florian@queze.net", "id": 149052, "name": "florian@queze.net", "real_name": "Florian Qu\u00e8ze [:florian]"}, {"email": "sledru@mozilla.com", "id": 495955, "name": "sledru@mozilla.com", "real_name": "Sylvestre Ledru [:sylvestre]"}], "cf_has_str": "---", "alias": null, "dupe_of": null, "flags": [{"requestee": "dao+bmo@mozilla.com", "status": "?", "name": "needinfo", "modification_date": "2018-05-17T08:10:48Z", "type_id": 800, "creation_date": "2018-05-17T08:10:48Z", "id": 1758017, "setter": "dao+bmo@mozilla.com"}], "last_change_time": "2018-06-04T14:29:31Z", "cf_status_firefox_esr60": "---", "assigned_to": "nobody@mozilla.org", "is_open": true, "resolution": "", "op_sys": "Unspecified", "cf_fx_points": "---", "history": [{"changes": [{"removed": "", "field_name": "cc", "added": "florian@queze.net"}], "who": "dholbert@mozilla.com", "when": "2018-05-16T21:23:42Z"}, {"changes": [{"removed": "--", "field_name": "priority", "added": "P3"}, {"removed": "", "field_name": "cc", "added": "dao+bmo@mozilla.com"}, {"removed": "", "field_name": "flagtypes.name", "added": "needinfo?(dao+bmo@mozilla.com)"}], "who": "dao+bmo@mozilla.com", "when": "2018-05-17T08:10:48Z"}, {"changes": [{"removed": "", "field_name": "keywords", "added": "regression"}, {"removed": "", "field_name": "cc", "added": "sledru@mozilla.com"}], "who": "sledru@mozilla.com", "when": "2018-05-18T12:13:42Z"}]}