{"cf_tracking_thunderbird_esr52": "---", "cf_tracking_firefox60": "---", "cf_tracking_firefox61": "---", "cf_tracking_firefox62": "---", "mentors_detail": [], "depends_on": [], "cf_tracking_seamonkey259": "---", "cf_tracking_seamonkey258": "---", "is_open": false, "keywords": ["regression"], "cf_tracking_seamonkey253": "---", "cf_last_resolved": "2018-05-27T12:37:46Z", "votes": 0, "cf_status_seamonkey253": "---", "is_confirmed": true, "is_creator_accessible": true, "cf_status_seamonkey258": "---", "cf_status_seamonkey259": "---", "cf_status_thunderbird_52": "---", "platform": "Unspecified", "cf_crash_signature": "", "cf_status_thunderbird_esr52": "affected", "cf_status_thunderbird_56": "---", "cf_status_thunderbird_57": "---", "cf_status_thunderbird_54": "---", "cf_status_thunderbird_58": "---", "cf_status_thunderbird_59": "---", "cf_tracking_firefox_esr60": "---", "cf_tracking_thunderbird_esr60": "---", "cf_status_seamonkey249": "---", "summary": "In \"original HTML\" and \"simple HTML\" view the body of the message is placed outside <div class=moz-text-html>", "cf_status_seamonkey257esr": "---", "cf_tracking_seamonkey257esr": "---", "cf_tracking_thunderbird_62": "---", "attachments": [{"creator": "jorgk@jorgk.com", "is_obsolete": 1, "is_patch": 0, "flags": [], "content_type": "image/png", "id": 8979013}, {"creator": "ben.bucksch@beonex.com", "is_obsolete": 1, "is_patch": 1, "flags": [], "content_type": "text/plain", "id": 8979189}, {"creator": "ben.bucksch@beonex.com", "is_obsolete": 1, "is_patch": 1, "flags": [], "content_type": "text/plain", "id": 8979193}, {"creator": "jorgk@jorgk.com", "is_obsolete": 1, "is_patch": 1, "flags": [{"status": "-", "name": "review", "modification_date": "2018-05-21T11:57:01Z", "type_id": 4, "creation_date": "2018-05-21T11:57:01Z", "id": 1759427, "setter": "jorgk@jorgk.com"}], "content_type": "text/plain", "id": 8979203}, {"creator": "jorgk@jorgk.com", "is_obsolete": 1, "is_patch": 0, "flags": [], "content_type": "text/plain", "id": 8979247}, {"creator": "jorgk@jorgk.com", "is_obsolete": 1, "is_patch": 1, "flags": [], "content_type": "text/plain", "id": 8980843}, {"creator": "jorgk@jorgk.com", "is_obsolete": 1, "is_patch": 1, "flags": [{"status": "+", "name": "review", "modification_date": "2018-05-27T11:43:15Z", "type_id": 4, "creation_date": "2018-05-26T17:08:29Z", "id": 1762124, "setter": "mkmelin+mozilla@iki.fi"}], "content_type": "text/plain", "id": 8980881}, {"creator": "jorgk@jorgk.com", "is_obsolete": 0, "is_patch": 1, "flags": [{"status": "+", "name": "review", "modification_date": "2018-05-27T12:26:32Z", "type_id": 4, "creation_date": "2018-05-27T12:26:32Z", "id": 1762220, "setter": "jorgk@jorgk.com"}], "content_type": "text/plain", "id": 8980970}], "cf_tracking_thunderbird_60": "---", "cf_tracking_thunderbird_61": "---", "creation_time": "2018-05-19T09:45:42Z", "cf_tracking_firefox_relnote": "---", "assigned_to_detail": {"email": "jorgk@jorgk.com", "id": 176914, "name": "jorgk@jorgk.com", "real_name": "Jorg K (GMT+2)"}, "comments": [{"text": "Created attachment 8979013\nsimple HTML not in div tag.png\n\nWorking on bug 1419417 we noticed that the message body of messages when viewed in \"Simple HTML\" view is placed outside the <div class=moz-text-html> tag. This is wrong and as a consequence, CSS is not applied properly to the body, including margins and spacing.", "author": "jorgk@jorgk.com", "id": 13290842, "time": "2018-05-19T09:45:42Z"}, {"text": "Created attachment 8979189\nMove </div> to end (for trunk)", "author": "ben.bucksch@beonex.com", "id": 13293714, "time": "2018-05-21T10:08:45Z"}, {"text": "Comment on attachment 8979189\nMove </div> to end (for trunk)\n\nReview of attachment 8979189:\n-----------------------------------------------------------------\n\nThanks for the research, I'll try it after lunch.\n\n::: mailnews/mime/src/mimethsa.cpp\n@@ +120,1 @@\n>                               resultCStr.BeginWriting(),\n\nNit: Indentation a little questionable here, no?", "author": "jorgk@jorgk.com", "id": 13293741, "time": "2018-05-21T10:27:14Z"}, {"text": "Created attachment 8979193\nMove </div> to end, v1.1 (for trunk)\n\n(just add linebreaks in commit message)", "author": "ben.bucksch@beonex.com", "id": 13293742, "time": "2018-05-21T10:27:39Z"}, {"text": "> Nit: Indentation a little questionable here, no?\n\nThat's existing code and formatting. It was there before.\n\nPlease consider that it look me 1.5 hours (!) of work just to create these patches in a form that you like. Not coding, just to make the diffs for you in the form that you requested. Each change, patch and review round is very expensive. I do not want to make such changes for trivial, significant matters like whitespace. Esp. for existing code.\n\nAs we discussed on chat, we can revisit and fix the style of the entire libmime module. But after discussion, and as a separate, single commit for the entire module.\n\nWikipedia \"Atomic commit\": \"...becomes especially important when making format changes to the source code. If format and functional changes are combined it becomes very difficult to identify useful changes.\"", "author": "ben.bucksch@beonex.com", "id": 13293751, "time": "2018-05-21T10:42:21Z"}, {"text": "Ben, in C-C and M-C we adjust indentation if the surrounding code changes, some recent examples:\nhttps://hg.mozilla.org/comm-central/rev/f378ff5bbc894ff9863dec27d27f99947726f096#l3.12\nhttps://hg.mozilla.org/mozilla-central/rev/c58f0b4dd849#l143.180\n\nThat's independent of how much time you spent fighting with HG.\n\nSo there are a few options:\n1) I make the change.\n2) You make the change.\n3) It's technically an r- and we can't move forward.\n4) We keep discussing the issue.\n\nPlease authorise 1) or make 2) yourself.", "author": "jorgk@jorgk.com", "id": 13293801, "time": "2018-05-21T11:11:48Z"}, {"text": "Created attachment 8979203\nMove </div> to end, v1.1 (for trunk) + indentation and commit message fix\n\nSadly this doesn't work at all. I tested this with attachment 8975458 from bug 1419417 and now the body doesn't show any more at all.\n\nI fixed the indentation I requested and also the commit message. I would immensely appreciate not having to make those changes again.", "author": "jorgk@jorgk.com", "id": 13293841, "time": "2018-05-21T11:57:01Z"}, {"text": "Richard, looking at this again, class moz-text-html doesn't appear to have any CSS. So while the DOM is wrong, even if it were right, no CSS would apply. What am I missing?", "author": "jorgk@jorgk.com", "id": 13293929, "time": "2018-05-21T12:52:17Z"}, {"text": "Checked with the test message and without a patch from bug 1419417 and the standard CSS (html.css) is applied. But with \"Original HTML\" I see only the text \"Please answer to this email ...\" and no attachment lines. With \"Simple HTML\" I see no text but the two attachment lines.\n\nChecking with inspector I find the message text in \"Simple HTML\" nowhere.\n\nDo I need a patch from bug 1419417 for this testing? If yes, which should I use.", "author": "richard.marti@gmail.com", "id": 13293988, "time": "2018-05-21T13:27:41Z"}, {"text": "Richard, it's all very confusing right now. I just wanted to confirm that no CSS is defined for moz-text-html.", "author": "jorgk@jorgk.com", "id": 13293995, "time": "2018-05-21T13:31:15Z"}, {"text": "No special CSS is applied except the default html.css.", "author": "richard.marti@gmail.com", "id": 13294049, "time": "2018-05-21T13:53:03Z"}, {"text": "Created attachment 8979247\nmulti-html.eml\n\nThe patch works OK for a simple HTML mail, but this message here doesn't display anything but horizontal separators. Now the patch isn't right.", "author": "jorgk@jorgk.com", "id": 13294114, "time": "2018-05-21T14:14:58Z"}, {"text": "Now that bug 1419417 has landed, the HTML is placed incorrectly in the DOM for the \"original HTML\" and \"simple HTML\" views. We should fix that since it shows some logic error somewhere in MIME processing.\n\nBen, will you be continuing to work on this bug? If so, please try your patch on the message in attachment 8979247 and attachment 8979258. Or do a try run with your patch. If not, please unassign yourself.", "author": "jorgk@jorgk.com", "id": 13294547, "time": "2018-05-21T17:10:03Z"}, {"text": "Also, if you look at bug 1429491 comment #17 you will see that inserting stuff before the original HTML of the message is absolutely fatal since all the HTML we add leads to all e-mail being rendered in quirks mode. Is we want to correct this, we must stop inserting anything.\n\nSo maybe instead of deliberating how to get the closing </div> into position, we should scrap the <div> tag altogether, at least for \"original\" HTML.\n\nI forgot the NI: Ben, you'll be continuing here?", "author": "jorgk@jorgk.com", "id": 13294559, "time": "2018-05-21T17:16:03Z"}, {"text": "We'll remove that <div> in bug 1429491, so no action here.", "author": "jorgk@jorgk.com", "id": 13297560, "time": "2018-05-22T19:02:50Z"}, {"text": "Created attachment 8980843\ncall-superclass-eof-later.patch\n\nFor the record: This is Ben's suggestion to address the issue. It's is the difference between versions 4 and 5 of his patches from bug 1419417. Version 4 was landed since version 5 doesn't work. Some messages are not rendered correctly at all, like multi-html.eml, others, like a simple multipart/related (HTML+embedded image) crash in debug mode on assert. Tests also crash on assert.", "author": "jorgk@jorgk.com", "id": 13365780, "time": "2018-05-26T05:49:27Z"}, {"text": "I think this is generally the correct approach, yes. I might be wrong, but there might simply be a detail problem that's causing this. Could you look into the asserts, what's going on?", "author": "ben.bucksch@beonex.com", "id": 13365783, "time": "2018-05-26T06:00:24Z"}, {"text": "No I won't. You caused this regression in bug 1419417, so please fix it.", "author": "jorgk@jorgk.com", "id": 13365787, "time": "2018-05-26T06:38:24Z"}, {"text": "(In reply to Ben Bucksch (:BenB) from comment #16)\n> I think this is generally the correct approach, yes.\nI doubt this:\nhttps://dxr.mozilla.org/comm-central/search?q=Run+parent+method+first%2C+to+flush+out+any+buffered+data&redirect=true\n\nAlso note:\nhttps://dxr.mozilla.org/comm-central/rev/51678c5b0b3edd827c57a70f1c5baf02d44acead/mailnews/mime/src/mimethpl.cpp#65", "author": "jorgk@jorgk.com", "id": 13365789, "time": "2018-05-26T06:43:09Z"}, {"text": "OK, seems like I was wrong, then.", "author": "ben.bucksch@beonex.com", "id": 13365791, "time": "2018-05-26T06:58:47Z"}, {"text": "Thanks for finding this.", "author": "ben.bucksch@beonex.com", "id": 13365792, "time": "2018-05-26T06:59:03Z"}, {"text": "Here are a few ideas how to fix this:\n* In HTMLParsed (which is the main problem we have), you have a DOM tree. You can add the <div> to the DOM\n  after parsing and before serializing. That allows to add it in the proper place in the HTML document.\n* You could try to add a ParseEnd function to TextHTML base class and move the closing </div> there\n  instead of the ParseEOF(). I don't know whether that would work.\n* You remove the <div> from the TextHTML superclass and put it in the HTMLParsed and HTMLSanitized subclassed.\n  Not nice, but a quick fix and should work, because you control the order there.", "author": "ben.bucksch@beonex.com", "id": 13365889, "time": "2018-05-26T11:19:02Z"}, {"text": "Hint: If you can part with the <div>, there is code in attachment 8980767 that will apply the lang attribute directly to the body or html tags. That code is tested and working. Alternatively a hack along the lines of\nhttps://dxr.mozilla.org/comm-central/rev/51678c5b0b3edd827c57a70f1c5baf02d44acead/mailnews/mime/src/mimethpl.cpp#65\nmight do the trick.\n\nI'll leave it to the assignee to figure something out.", "author": "jorgk@jorgk.com", "id": 13365890, "time": "2018-05-26T11:21:09Z"}, {"text": "> If you can part with the <div>, there is code in attachment 8980767 [details] [diff] [review] that will\n> apply the lang attribute directly to the body or html tags. That code is tested and working.\n\nFWIW, I had rejected that patch because of the stylesheet changes, which break a lot of stuff, not because of the lang attribute, which was a good idea. Aside from the stylesheet, I think that patch is neat and a good start.\n\nInstead of putting the lang into the <body>, you could probably simply inject a <div> between the <body> and its child elements. That's what I meant with point 1 in comment 21. That would be the best possible fix.", "author": "ben.bucksch@beonex.com", "id": 13365895, "time": "2018-05-26T11:26:25Z"}, {"text": "(In reply to Ben Bucksch (:BenB) from comment #23)\n> Instead of putting the lang into the <body>, you could probably ...\nYou mean \"..., one could probably ...\".\n\nLooking forward to reviewing the patch. Thanks for taking the bug ;-)", "author": "jorgk@jorgk.com", "id": 13365921, "time": "2018-05-26T12:27:27Z"}, {"text": "Oh, I missed that, you unassigned yourself. That's a pity, so who's going to fix *your* regression now?", "author": "jorgk@jorgk.com", "id": 13365922, "time": "2018-05-26T12:28:26Z"}, {"text": "Created attachment 8980881\n1462895-fix-language-div.patch\n\nNote that looking for <body> doesn't work since we need to cater for\n  <body text=\"#000000\" bgcolor=\"#FFFFFF\">\n\nThis took 30 minutes to write, less time than the discussion around it :-(", "author": "jorgk@jorgk.com", "id": 13366071, "time": "2018-05-26T17:08:29Z"}, {"text": "Comment on attachment 8980881\n1462895-fix-language-div.patch\n\nReview of attachment 8980881:\n-----------------------------------------------------------------\n\n::: mailnews/mime/src/mimethtm.cpp\n@@ +186,5 @@\n> +  if (obj->options->format_out != nsMimeOutput::nsMimeMessageBodyDisplay &&\n> +      obj->options->format_out != nsMimeOutput::nsMimeMessagePrintOutput)\n> +    return;\n> +\n> +  // Insert <div class=\"moz-text-html\" lang=\"...\"> for the following two purposes:\n\nbut why not put the class=\"moz-text-html\" lang=\"...\" directly on the body?\n\n@@ +193,5 @@\n> +  //    which font to use.\n> +  // Make sure we have a <body> before we start.\n> +  int32_t index = message.Find(\"<body\");\n> +  if (index == kNotFound)\n> +    return;\n\nshouldn't this at least warn?\n|message| is assumed to be a serialized document, and should have a body\n\n@@ +216,5 @@\n> +  }\n> +\n> +  index = message.RFind(\"</body>\");\n> +  if (index != kNotFound)\n> +    message.Insert(NS_LITERAL_CSTRING(\"</div>\"), index);\n\ncan you explain what the logic is here?\n\nwhen do we not have a </body>? should it warn (or similar)?", "author": "mkmelin+mozilla@iki.fi", "id": 13366144, "time": "2018-05-26T19:42:18Z"}, {"text": "(In reply to Magnus Melin from comment #27)\n> > +  // Insert <div class=\"moz-text-html\" lang=\"...\"> for the following two purposes:\n> but why not put the class=\"moz-text-html\" lang=\"...\" directly on the body?\nBen wanted a div. So we're maintaining existing behaviour. To give the body a class is a strange idea from a web developer point of view, no? I'd rather not do that.\n\n> shouldn't this at least warn?\nWho would care?\n\n> |message| is assumed to be a serialized document, and should have a body\nMaybe not, if the message was empty? I don't know, but nsIDocument::GetBodyElement() can return null, so better safe than sorry.\n\n> > +  index = message.RFind(\"</body>\");\n> > +  if (index != kNotFound)\n> > +    message.Insert(NS_LITERAL_CSTRING(\"</div>\"), index);\n> can you explain what the logic is here?\nUmm, we look for the last </body> tag in the serialised output and insert a </div> before it, just like we inserted a <div> after the <body> tag. Looks pretty clear to me.\n\n> when do we not have a </body>? should it warn (or similar)?\nAgain, no one will see the warning.", "author": "jorgk@jorgk.com", "id": 13366147, "time": "2018-05-26T19:52:06Z"}, {"text": "(In reply to Jorg K (GMT+2) (bustage-fix and urgent reviews only) from comment #28)\n> To give the body a class is a strange idea from a web developer point of view, no? \n\nI don't see anything strange with that. Semantically its' more correct since you don't mess with the original intent. You can even easily be breaking css rules of the sender's since you modify the document to add a <div>. (Though it might not be that important, since <style> is pretty unsupported in mail clients.)\n\n \n> > shouldn't this at least warn?\n> Who would care?\n\nSomeone wondering why the message disappeared? :)\nAnyway, please at least document it very clearly that <body> must be included.", "author": "mkmelin+mozilla@iki.fi", "id": 13366480, "time": "2018-05-27T11:06:48Z"}, {"text": "Comment on attachment 8980881\n1462895-fix-language-div.patch\n\nReview of attachment 8980881:\n-----------------------------------------------------------------\n\nI'll let you decide how much of the comments you want to address. r=mkmelin", "author": "mkmelin+mozilla@iki.fi", "id": 13366505, "time": "2018-05-27T11:43:15Z"}, {"text": "Other MIME classes add <div>s, for example:\n\n<body>\n<div class=\"moz-text-plain\" wrap=\"true\" graphical-quote=\"true\" style=\"font-family: -moz-fixed; font-size: 14px;\" lang=\"x-unicode\">\n\nPlease file a follow-up to correct the lot.", "author": "jorgk@jorgk.com", "id": 13366513, "time": "2018-05-27T12:18:44Z"}, {"text": "Created attachment 8980970\n1462895-fix-language-div.patch (v2)\n\nAddressed some comments ;-)", "author": "jorgk@jorgk.com", "id": 13366517, "time": "2018-05-27T12:26:32Z"}, {"text": "Pushed by mozilla@jorgk.com:\nhttps://hg.mozilla.org/comm-central/rev/a4a57af137c4\nfix insertion of <div class=\"moz-text-html\" lang=\"...\">. r=mkmelin", "author": "pulsebot@bots.tld", "id": 13366523, "time": "2018-05-27T12:37:46Z"}, {"text": "Thanks, J\u00f6rg, for picking this up.\n\nAs to the patch here, I think this string replacement here is too fragile. I'm particularly worried about cases where we might not have any body, or 2 body elements.\n\nWe have a DOM tree, why not use that to insert the <div> properly? I think your attachment 8980767 was a good start, see comment 23.", "author": "ben.bucksch@beonex.com", "id": 13366526, "time": "2018-05-27T12:39:17Z"}, {"text": "Duh, edit conflict, you landed just in the moment while I was typing my comment.", "author": "ben.bucksch@beonex.com", "id": 13366527, "time": "2018-05-27T12:40:07Z"}, {"text": "> Other MIME classes add <div>s, for example:\n> <body>\n> <div class=\"moz-text-plain\" wrap=\"true\" graphical-quote=\"true\" style=\"font-family: -moz-fixed; font-size: 14px;\" lang=\"x-unicode\">\n> Please file a follow-up to correct the lot.\n\nPlease CC me, if you file bugs. But the above <div> looks correct to me. If you modify that, you are likely to break some things that you don't even know exist.", "author": "ben.bucksch@beonex.com", "id": 13366536, "time": "2018-05-27T12:46:43Z"}, {"text": "TB 60 beta 7 (BETA_60_CONTINUATION branch):\nhttps://hg.mozilla.org/releases/comm-beta/rev/401d57f937ac62f88646941698f06c9f09695cad", "author": "jorgk@jorgk.com", "id": 13366537, "time": "2018-05-27T12:46:43Z"}, {"text": "(In reply to Ben Bucksch (:BenB) from comment #34)\n> As to the patch here, I think this string replacement here is too fragile.\n> I'm particularly worried about cases where we might not have any body, or 2\n> body elements.\nFor the sanitised case we don't have a DOM, so we need string manipulation anyway (of which MIME does heaps already).\nShuffling all the content of the body into a div is a lot of work on a DOM level, but only a few lines in string manipulation. The string passed in is always result of a Gecko serialisation or sanitisation, so if should have one or no body element. If there is no body, we obviously don't have to insert anything.\n \n> We have a DOM tree, why not use that to insert the <div> properly?\nSee above, a lot of manipulation inserting a <div> and then shuffling the <body>'s content into it.", "author": "jorgk@jorgk.com", "id": 13366542, "time": "2018-05-27T12:51:46Z"}, {"text": "> For the sanitised case we don't have a DOM\n\nYes. You'd need the string messing in that case. But at least the normal mode would be saved.\n\n> > We have a DOM tree, why not use that to insert the <div> properly?\n\n> See above\n\nWhere above? Which comment?\n\nJust create a new DIV, iterate over body children, move them to the <div>, then put the <div> underneath <body>.\n\nAnyway, that was a suggestion to write this in a clean way. Your patch fixes the bug, that's nice.\n\nI simply worry that there are cases where the HTML string manipulation fails, e.g. when there is no body or more than 1 body.", "author": "ben.bucksch@beonex.com", "id": 13366550, "time": "2018-05-27T12:59:28Z"}, {"text": "(In reply to Ben Bucksch (:BenB) from comment #39)\n> > See above\n> Where above? Which comment?\nSame comment, just the paragraph above.\n\n> Just create a new DIV, iterate over body children, move them to the <div>,\n> then put the <div> underneath <body>.\nExactly. And how error prone is that and how many CPU cycles does this burn compared to a simple string insertion?", "author": "jorgk@jorgk.com", "id": 13366565, "time": "2018-05-27T13:09:09Z"}, {"text": "That's much safer than the string messing, and it's a simple DOM manipulation.\n\nAnyway... If your fix works in all cases (it appears it does), it's OK. Thanks for the fix.", "author": "ben.bucksch@beonex.com", "id": 13366584, "time": "2018-05-27T14:08:58Z"}, {"text": "Pushed by mozilla@jorgk.com:\nhttps://hg.mozilla.org/comm-central/rev/e48189835da7\nFollow-up: Use FindChar() instead of Find(). r=me", "author": "pulsebot@bots.tld", "id": 13395075, "time": "2018-06-07T22:14:09Z"}, {"text": "https://hg.mozilla.org/releases/comm-beta/rev/1ca7373fac5894d1075289ca65972eba2f217e48\n\nThis was actually quite fatal:\nFind(string, ignoreCase, offset) was called with Find(string, offset) and no one noticed :-(\nUsing FindChar(char, offset) is actually right now.\nSo in effect, the <div> got inserted after the <html> tag, not the <body> tag, but apparently Gecko didn't mind.", "author": "jorgk@jorgk.com", "id": 13395083, "time": "2018-06-07T22:19:31Z"}], "version": "Trunk", "qa_contact": "", "see_also": [], "component": "MIME", "cf_status_firefox62": "---", "cf_status_firefox61": "---", "cf_status_firefox60": "---", "cf_qa_whiteboard": "", "whiteboard": "", "op_sys": "Unspecified", "groups": [], "classification": "Components", "cc": ["acelists@atlas.sk", "ben.bucksch@beonex.com", "mcastelluccio@mozilla.com", "mkmelin+mozilla@iki.fi", "richard.marti@gmail.com"], "cf_status_firefox_esr60": "---", "cf_user_story": "", "cf_status_thunderbird_53": "---", "creator": "jorgk@jorgk.com", "priority": "--", "comment_count": 44, "cf_tracking_firefox_esr52": "---", "cf_fx_iteration": "---", "cf_tracking_thunderbird_59": "---", "cf_tracking_thunderbird_58": "---", "cf_tracking_thunderbird_57": "---", "cf_tracking_thunderbird_56": "---", "cf_tracking_thunderbird_54": "---", "cf_tracking_thunderbird_53": "---", "cf_tracking_thunderbird_52": "---", "is_cc_accessible": true, "cc_detail": [{"email": "acelists@atlas.sk", "id": 97012, "name": "acelists@atlas.sk", "real_name": ":aceman"}, {"email": "ben.bucksch@beonex.com", "id": 22599, "name": "ben.bucksch@beonex.com", "real_name": "Ben Bucksch (:BenB)"}, {"email": "mcastelluccio@mozilla.com", "id": 420453, "name": "mcastelluccio@mozilla.com", "real_name": "Marco Castelluccio [:marco]"}, {"email": "mkmelin+mozilla@iki.fi", "id": 101158, "name": "mkmelin+mozilla@iki.fi", "real_name": "Magnus Melin"}, {"email": "richard.marti@gmail.com", "id": 282357, "name": "richard.marti@gmail.com", "real_name": "Richard Marti (:Paenglab)"}], "dupe_of": null, "cf_fx_points": "---", "history": [{"changes": [{"removed": "NEW", "field_name": "status", "added": "ASSIGNED"}, {"removed": "nobody@mozilla.org", "field_name": "assigned_to", "added": "ben.bucksch@beonex.com"}], "who": "ben.bucksch@beonex.com", "when": "2018-05-21T10:08:45Z"}, {"changes": [{"field_name": "attachments.isobsolete", "removed": "0", "attachment_id": 8979189, "added": "1"}], "who": "ben.bucksch@beonex.com", "when": "2018-05-21T10:27:39Z"}, {"changes": [{"field_name": "attachments.isobsolete", "removed": "0", "attachment_id": 8979193, "added": "1"}, {"field_name": "flagtypes.name", "removed": "", "attachment_id": 8979203, "added": "review-"}], "who": "jorgk@jorgk.com", "when": "2018-05-21T11:57:01Z"}, {"changes": [{"removed": "", "field_name": "flagtypes.name", "added": "needinfo?(richard.marti@gmail.com)"}], "who": "jorgk@jorgk.com", "when": "2018-05-21T12:52:17Z"}, {"changes": [{"removed": "needinfo?(richard.marti@gmail.com)", "field_name": "flagtypes.name", "added": ""}], "who": "richard.marti@gmail.com", "when": "2018-05-21T13:27:41Z"}, {"changes": [{"removed": "In \"simple HTML\" view the body of the message is placed outside <div class=moz-text-html>", "field_name": "summary", "added": "In \"original HTML\" and \"simple HTML\" view the body of the message is placed outside <div class=moz-text-html>"}], "who": "jorgk@jorgk.com", "when": "2018-05-21T17:10:03Z"}, {"changes": [{"removed": "", "field_name": "flagtypes.name", "added": "needinfo?(ben.bucksch@beonex.com)"}], "who": "jorgk@jorgk.com", "when": "2018-05-21T17:16:03Z"}, {"changes": [{"removed": "ASSIGNED", "field_name": "status", "added": "RESOLVED"}, {"removed": "", "field_name": "resolution", "added": "WONTFIX"}, {"removed": "needinfo?(ben.bucksch@beonex.com)", "field_name": "flagtypes.name", "added": ""}, {"removed": "", "field_name": "cf_last_resolved", "added": "2018-05-22 19:02:50"}], "who": "jorgk@jorgk.com", "when": "2018-05-22T19:02:50Z"}, {"changes": [{"removed": "RESOLVED", "field_name": "status", "added": "REOPENED"}, {"removed": "WONTFIX", "field_name": "resolution", "added": ""}], "who": "jorgk@jorgk.com", "when": "2018-05-26T10:06:16Z"}, {"changes": [{"removed": "REOPENED", "field_name": "status", "added": "ASSIGNED"}, {"removed": "normal", "field_name": "severity", "added": "critical"}], "who": "jorgk@jorgk.com", "when": "2018-05-26T10:06:28Z"}, {"changes": [{"removed": "ASSIGNED", "field_name": "status", "added": "NEW"}, {"removed": "ben.bucksch@beonex.com", "field_name": "assigned_to", "added": "nobody@mozilla.org"}, {"removed": "critical", "field_name": "severity", "added": "major"}], "who": "ben.bucksch@beonex.com", "when": "2018-05-26T11:19:02Z"}, {"changes": [{"field_name": "attachments.isobsolete", "removed": "0", "attachment_id": 8980843, "added": "1"}], "who": "ben.bucksch@beonex.com", "when": "2018-05-26T11:21:31Z"}, {"changes": [{"removed": "NEW", "field_name": "status", "added": "ASSIGNED"}, {"removed": "nobody@mozilla.org", "field_name": "assigned_to", "added": "jorgk@jorgk.com"}], "who": "jorgk@jorgk.com", "when": "2018-05-26T16:35:55Z"}, {"changes": [{"field_name": "attachments.isobsolete", "removed": "0", "attachment_id": 8979203, "added": "1"}], "who": "jorgk@jorgk.com", "when": "2018-05-26T17:05:20Z"}, {"changes": [{"field_name": "attachments.isobsolete", "removed": "0", "attachment_id": 8979013, "added": "1"}, {"field_name": "attachments.isobsolete", "removed": "0", "attachment_id": 8979247, "added": "1"}, {"field_name": "flagtypes.name", "removed": "", "attachment_id": 8980881, "added": "review?(acelists@atlas.sk), review?(mkmelin+mozilla@iki.fi)"}], "who": "jorgk@jorgk.com", "when": "2018-05-26T17:08:29Z"}, {"changes": [{"field_name": "flagtypes.name", "removed": "review?(acelists@atlas.sk), review?(mkmelin+mozilla@iki.fi)", "attachment_id": 8980881, "added": "review+"}], "who": "mkmelin+mozilla@iki.fi", "when": "2018-05-27T11:43:15Z"}, {"changes": [{"field_name": "attachments.isobsolete", "removed": "0", "attachment_id": 8980881, "added": "1"}, {"field_name": "flagtypes.name", "removed": "", "attachment_id": 8980970, "added": "review+"}], "who": "jorgk@jorgk.com", "when": "2018-05-27T12:26:32Z"}, {"changes": [{"removed": "ASSIGNED", "field_name": "status", "added": "RESOLVED"}, {"removed": "", "field_name": "resolution", "added": "FIXED"}, {"removed": "2018-05-22 19:02:50", "field_name": "cf_last_resolved", "added": "2018-05-27 12:37:46"}], "who": "pulsebot@bots.tld", "when": "2018-05-27T12:37:46Z"}, {"changes": [{"removed": "---", "field_name": "target_milestone", "added": "Thunderbird 62.0"}], "who": "jorgk@jorgk.com", "when": "2018-05-27T12:38:15Z"}, {"changes": [{"removed": "---", "field_name": "cf_status_thunderbird_esr52", "added": "affected"}, {"removed": "---", "field_name": "cf_status_thunderbird_esr60", "added": "affected"}, {"removed": "---", "field_name": "cf_status_thunderbird_60", "added": "fixed"}, {"removed": "---", "field_name": "cf_status_thunderbird_61", "added": "affected"}, {"removed": "---", "field_name": "cf_status_thunderbird_62", "added": "fixed"}], "who": "jorgk@jorgk.com", "when": "2018-05-27T12:51:46Z"}, {"changes": [{"removed": "", "field_name": "keywords", "added": "regression"}, {"removed": "", "field_name": "cc", "added": "mcastelluccio@mozilla.com"}], "who": "mcastelluccio@mozilla.com", "when": "2018-06-08T12:18:07Z"}], "id": 1462895, "severity": "major", "status": "RESOLVED", "product": "MailNews Core", "cf_status_firefox_esr52": "---", "blocks": [1419417], "cf_tracking_seamonkey249": "---", "target_milestone": "Thunderbird 62.0", "url": "", "resolution": "FIXED", "creator_detail": {"email": "jorgk@jorgk.com", "id": 176914, "name": "jorgk@jorgk.com", "real_name": "Jorg K (GMT+2)"}, "mentors": [], "last_change_time": "2018-06-08T12:18:07Z", "alias": null, "flags": [], "assigned_to": "jorgk@jorgk.com", "cf_status_thunderbird_esr60": "affected", "cf_status_thunderbird_62": "fixed", "cf_status_thunderbird_61": "affected", "cf_status_thunderbird_60": "fixed"}